Workbook
Name Slicer_Region: #N/A

Sheet Orders
A1: Row ID | B1: Order Priority | C1: Discount | D1: Unit Price | E1: Shipping Cost | F1: Customer ID | G1: Customer Name | H1: Ship Mode | I1: Customer Segment | J1: Product Category | K1: Product Sub-Category | L1: Product Container | M1: Product Name | N1: Product Base Margin | O1: Country | P1: Region | Q1: State or Province | R1: City | S1: Postal Code | T1: Order Date | U1: Ship Date | V1: Profit | W1: Quantity ordered new | X1: Sales | Y1: Order ID | Z1: Month | AA1: Profit margin | AB1: Returned | AC1: Manager
A2: 20847 | B2: High | C2: 0.01 | D2: 2.84 | E2: 0.93 | F2: 3 | G2: Bonnie Potter | H2: Express Air | I2: Corporate | J2: Office Supplies | K2: Pens & Art Supplies | L2: Wrap Bag | M2: SANFORD Liquid Accent™ Tank-Style Highlighters | N2: 0.54 | O2: United States | P2: West | Q2: Washington | R2: Anacortes | S2: 98221 | T2: 42011 | U2: 42012 | V2: 4.56 | W2: 4 | X2: 13.01 | Y2: 88522 | Z2: =TEXT(Superstone_data[[#This Row],[Order Date]],"mmm") -> Jan | AA2: =Superstone_data[[#This Row],[Profit]]/Superstone_data[[#This Row],[Sales]] -> 0.35049962 | AB2: =IFERROR(VLOOKUP(Superstone_data[[#This Row],[Order ID]], Returns!A:B, 2, FALSE), "No") -> No | AC2: =VLOOKUP(Superstone_data[[#This Row],[Region]], Users!A:B, 2, FALSE) -> William
A3: 20228 | B3: Not Specified | C3: 0.02 | D3: 500.98 | E3: 26 | F3: 5 | G3: Ronnie Proctor | H3: Delivery Truck | I3: Home Office | J3: Furniture | K3: Chairs & Chairmats | L3: Jumbo Drum | M3: Global Troy™ Executive Leather Low-Back Tilter | N3: 0.6 | O3: United States | P3: West | Q3: California | R3: San Gabriel | S3: 91776 | T3: 42168 | U3: 42170 | V3: 4390.3665 | W3: 12 | X3: 6362.85 | Y3: 90193 | Z3: =TEXT(Superstone_data[[#This Row],[Order Date]],"mmm") -> Jun | AA3: =Superstone_data[[#This Row],[Profit]]/Superstone_data[[#This Row],[Sales]] -> 0.69 | AB3: =IFERROR(VLOOKUP(Superstone_data[[#This Row],[Order ID]], Returns!A:B, 2, FALSE), "No") -> No | AC3: =VLOOKUP(Superstone_data[[#This Row],[Region]], Users!A:B, 2, FALSE) -> William
A4: 21776 | B4: Critical | C4: 0.06 | D4: 9.48 | E4: 7.29 | F4: 11 | G4: Marcus Dunlap | H4: Regular Air | I4: Home Office | J4: Furniture | K4: Office Furnishings | L4: Small Pack | M4: DAX Two-Tone Rosewood/Black Document Frame, Desktop, 5 x 7 | N4: 0.45 | O4: United States | P4: East | Q4: New Jersey | R4: Roselle | S4: 7203 | T4: 42050 | U4: 42052 | V4: -53.8096 | W4: 22 | X4: 211.15 | Y4: 90192 | Z4: =TEXT(Superstone_data[[#This Row],[Order Date]],"mmm") -> Feb | AA4: =Superstone_data[[#This Row],[Profit]]/Superstone_data[[#This Row],[Sales]] -> -0.25484063 | AB4: =IFERROR(VLOOKUP(Superstone_data[[#This Row],[Order ID]], Returns!A:B, 2, FALSE), "No") -> No | AC4: =VLOOKUP(Superstone_data[[#This Row],[Region]], Users!A:B, 2, FALSE) -> Erin
A5: 24844 | B5: Medium | C5: 0.09 | D5: 78.69 | E5: 19.99 | F5: 14 | G5: Gwendolyn F Tyson | H5: Regular Air | I5: Small Business | J5: Furniture | K5: Office Furnishings | L5: Small Box | M5: Howard Miller 12-3/4 Diameter Accuwave DS ™ Wall Clock | N5: 0.43 | O5: United States | P5: Central | Q5: Minnesota | R5: Prior Lake | S5: 55372 | T5: 42136 | U5: 42138 | V5: 803.4705 | W5: 16 | X5: 1164.45 | Y5: 86838 | Z5: =TEXT(Superstone_data[[#This Row],[Order Date]],"mmm") -> May | AA5: =Superstone_data[[#This Row],[Profit]]/Superstone_data[[#This Row],[Sales]] -> 0.69 | AB5: =IFERROR(VLOOKUP(Superstone_data[[#This Row],[Order ID]], Returns!A:B, 2, FALSE), "No") -> No | AC5: =VLOOKUP(Superstone_data[[#This Row],[Region]], Users!A:B, 2, FALSE) -> Chris
A6: 24846 | B6: Medium | C6: 0.08 | D6: 3.28 | E6: 2.31 | F6: 14 | G6: Gwendolyn F Tyson | H6: Regular Air | I6: Small Business | J6: Office Supplies | K6: Pens & Art Supplies | L6: Wrap Bag | M6: Newell 321 | N6: 0.56 | O6: United States | P6: Central | Q6: Minnesota | R6: Prior Lake | S6: 55372 | T6: 42136 | U6: 42137 | V6: -24.03 | W6: 7 | X6: 22.23 | Y6: 86838 | Z6: =TEXT(Superstone_data[[#This Row],[Order Date]],"mmm") -> May | AA6: =Superstone_data[[#This Row],[Profit]]/Superstone_data[[#This Row],[Sales]] -> -1.0809717 | AB6: =IFERROR(VLOOKUP(Superstone_data[[#This Row],[Order ID]], Returns!A:B, 2, FALSE), "No") -> No | AC6: =VLOOKUP(Superstone_data[[#This Row],[Region]], Users!A:B, 2, FALSE) -> Chris
A7: 24847 | B7: Medium | C7: 0.05 | D7: 3.28 | E7: 4.2 | F7: 14 | G7: Gwendolyn F Tyson | H7: Regular Air | I7: Small Business | J7: Office Supplies | K7: Pens & Art Supplies | L7: Wrap Bag | M7: Newell 351 | N7: 0.56 | O7: United States | P7: Central | Q7: Minnesota | R7: Prior Lake | S7: 55372 | T7: 42136 | U7: 42137 | V7: -37.03 | W7: 4 | X7: 13.99 | Y7: 86838 | Z7: =TEXT(Superstone_data[[#This Row],[Order Date]],"mmm") -> May | AA7: =Superstone_data[[#This Row],[Profit]]/Superstone_data[[#This Row],[Sales]] -> -2.6468906 | AB7: =IFERROR(VLOOKUP(Superstone_data[[#This Row],[Order ID]], Returns!A:B, 2, FALSE), "No") -> No | AC7: =VLOOKUP(Superstone_data[[#This Row],[Region]], Users!A:B, 2, FALSE) -> Chris
A8: 24848 | B8: Medium | C8: 0.05 | D8: 3.58 | E8: 1.63 | F8: 14 | G8: Gwendolyn F Tyson | H8: Regular Air | I8: Small Business | J8: Office Supplies | K8: Rubber Bands | L8: Wrap Bag | M8: OIC Colored Binder Clips, Assorted Sizes | N8: 0.36 | O8: United States | P8: Central | Q8: Minnesota | R8: Prior Lake | S8: 55372 | T8: 42136 | U8: 42137 | V8: -0.71 | W8: 4 | X8: 14.26 | Y8: 86838 | Z8: =TEXT(Superstone_data[[#This Row],[Order Date]],"mmm") -> May | AA8: =Superstone_data[[#This Row],[Profit]]/Superstone_data[[#This Row],[Sales]] -> -0.049789621 | AB8: =IFERROR(VLOOKUP(Superstone_data[[#This Row],[Order ID]], Returns!A:B, 2, FALSE), "No") -> No | AC8: =VLOOKUP(Superstone_data[[#This Row],[Region]], Users!A:B, 2, FALSE) -> Chris
A9: 18181 | B9: Critical | C9: 0 | D9: 4.42 | E9: 4.99 | F9: 15 | G9: Timothy Reese | H9: Regular Air | I9: Small Business | J9: Office Supplies | K9: Envelopes | L9: Small Box | M9: Grip Seal Envelopes | N9: 0.38 | O9: United States | P9: East | Q9: New York | R9: Smithtown | S9: 11787 | T9: 42102 | U9: 42103 | V9: -59.82 | W9: 7 | X9: 33.47 | Y9: 86837 | Z9: =TEXT(Superstone_data[[#This Row],[Order Date]],"mmm") -> Apr | AA9: =Superstone_data[[#This Row],[Profit]]/Superstone_data[[#This Row],[Sales]] -> -1.7872722 | AB9: =IFERROR(VLOOKUP(Superstone_data[[#This Row],[Order ID]], Returns!A:B, 2, FALSE), "No") -> No | AC9: =VLOOKUP(Superstone_data[[#This Row],[Region]], Users!A:B, 2, FALSE) -> Erin
A10: 20925 | B10: Medium | C10: 0.01 | D10: 35.94 | E10: 6.66 | F10: 15 | G10: Timothy Reese | H10: Regular Air | I10: Small Business | J10: Office Supplies | K10: Envelopes | L10: Small Box | M10: Tyvek ® Top-Opening Peel & Seel ® Envelopes, Gray | N10: 0.4 | O10: United States | P10: East | Q10: New York | R10: Smithtown | S10: 11787 | T10: 42152 | U10: 42152 | V10: 261.8757 | W10: 10 | X10: 379.53 | Y10: 86839 | Z10: =TEXT(Superstone_data[[#This Row],[Order Date]],"mmm") -> May | AA10: =Superstone_data[[#This Row],[Profit]]/Superstone_data[[#This Row],[Sales]] -> 0.69 | AB10: =IFERROR(VLOOKUP(Superstone_data[[#This Row],[Order ID]], Returns!A:B, 2, FALSE), "No") -> No | AC10: =VLOOKUP(Superstone_data[[#This Row],[Region]], Users!A:B, 2, FALSE) -> Erin
A11: 26267 | B11: High | C11: 0.04 | D11: 2.98 | E11: 1.58 | F11: 16 | G11: Sarah Ramsey | H11: Regular Air | I11: Small Business | J11: Office Supplies | K11: Rubber Bands | L11: Wrap Bag | M11: Staples Gold Paper Clips | N11: 0.39 | O11: United States | P11: East | Q11: New York | R11: Syracuse | S11: 13210 | T11: 42047 | U11: 42050 | V11: 2.63 | W11: 6 | X11: 18.8 | Y11: 86836 | Z11: =TEXT(Superstone_data[[#This Row],[Order Date]],"mmm") -> Feb | AA11: =Superstone_data[[#This Row],[Profit]]/Superstone_data[[#This Row],[Sales]] -> 0.13989362 | AB11: =IFERROR(VLOOKUP(Superstone_data[[#This Row],[Order ID]], Returns!A:B, 2, FALSE), "No") -> No | AC11: =VLOOKUP(Superstone_data[[#This Row],[Region]], Users!A:B, 2, FALSE) -> Erin
A12: 26268 | B12: High | C12: 0.05 | D12: 115.99 | E12: 2.5 | F12: 16 | G12: Sarah Ramsey | H12: Regular Air | I12: Small Business | J12: Technology | K12: Telephones and Communication | L12: Small Box | M12: StarTAC 7797 | N12: 0.55 | O12: United States | P12: East | Q12: New York | R12: Syracuse | S12: 13210 | T12: 42047 | U12: 42049 | V12: 652.7331 | W12: 10 | X12: 945.99 | Y12: 86836 | Z12: =TEXT(Superstone_data[[#This Row],[Order Date]],"mmm") -> Feb | AA12: =Superstone_data[[#This Row],[Profit]]/Superstone_data[[#This Row],[Sales]] -> 0.69 | AB12: =IFERROR(VLOOKUP(Superstone_data[[#This Row],[Order ID]], Returns!A:B, 2, FALSE), "No") -> No | AC12: =VLOOKUP(Superstone_data[[#This Row],[Region]], Users!A:B, 2, FALSE) -> Erin
A13: 23890 | B13: High | C13: 0.05 | D13: 26.48 | E13: 6.93 | F13: 18 | G13: Laurie Hanna | H13: Regular Air | I13: Small Business | J13: Furniture | K13: Office Furnishings | L13: Small Box | M13: DAX Natural Wood-Tone Poster Frame | N13: 0.49 | O13: United States | P13: West | Q13: Montana | R13: Helena | S13: 59601 | T13: 42139 | U13: 42140 | V13: 314.4813 | W13: 17 | X13: 455.77 | Y13: 90031 | Z13: =TEXT(Superstone_data[[#This Row],[Order Date]],"mmm") -> May | AA13: =Superstone_data[[#This Row],[Profit]]/Superstone_data[[#This Row],[Sales]] -> 0.69 | AB13: =IFERROR(VLOOKUP(Superstone_data[[#This Row],[Order ID]], Returns!A:B, 2, FALSE), "No") -> No | AC13: =VLOOKUP(Superstone_data[[#This Row],[Region]], Users!A:B, 2, FALSE) -> William
... A182: 19158 | B182: Medium | C182: 0.01 | D182: 29.1 | E182: 4 | F182: 331 | G182: Bradley Pollock | H182: Express Air | I182: Home Office | J182: Technology | K182: Computer Peripherals | L182: Small Box | M182: Acco Keyboard-In-A-Box® | N182: 0.78 | O182: United States | P182: East | Q182: New Hampshire | R182: Goffstown | S182: 3045 | T182: 42108 | U182: 42110 | V182: -22.82 | W182: 8 | X182: 243.32 | Y182: 89726 | Z182: =TEXT(Superstone_data[[#This Row],[Order Date]],"mmm") -> Apr | AA182: =Superstone_data[[#This Row],[Profit]]/Superstone_data[[#This Row],[Sales]] -> -0.093785961 | AB182: =IFERROR(VLOOKUP(Superstone_data[[#This Row],[Order ID]], Returns!A:B, 2, FALSE), "No") -> No | AC182: =VLOOKUP(Superstone_data[[#This Row],[Region]], Users!A:B, 2, FALSE) -> Erin
A183: 18261 | B183: Critical | C183: 0.06 | D183: 276.2 | E183: 24.49 | F183: 335 | G183: Curtis O'Connell | H183: Regular Air | I183: Corporate | J183: Furniture | K183: Chairs & Chairmats | L183: Large Box | M183: SAFCO Arco Folding Chair | O183: United States | P183: West | Q183: Oregon | R183: Medford | S183: 97504 | T183: 42128 | U183: 42129 | V183: 2639.4708 | W183: 14 | X183: 3825.32 | Y183: 87277 | Z183: =TEXT(Superstone_data[[#This Row],[Order Date]],"mmm") -> May | AA183: =Superstone_data[[#This Row],[Profit]]/Superstone_data[[#This Row],[Sales]] -> 0.69 | AB183: =IFERROR(VLOOKUP(Superstone_data[[#This Row],[Order ID]], Returns!A:B, 2, FALSE), "No") -> No | AC183: =VLOOKUP(Superstone_data[[#This Row],[Region]], Users!A:B, 2, FALSE) -> William
A184: 18262 | B184: Critical | C184: 0.09 | D184: 6.28 | E184: 5.29 | F184: 335 | G184: Curtis O'Connell | H184: Regular Air | I184: Corporate | J184: Furniture | K184: Office Furnishings | L184: Small Box | M184: Eldon® 200 Class™ Desk Accessories, Burgundy | N184: 0.43 | O184: United States | P184: West | Q184: Oregon | R184: Medford | S184: 97504 | T184: 42128 | U184: 42128 | V184: -5.2 | W184: 1 | X184: 8.53 | Y184: 87277 | Z184: =TEXT(Superstone_data[[#This Row],[Order Date]],"mmm") -> May | AA184: =Superstone_data[[#This Row],[Profit]]/Superstone_data[[#This Row],[Sales]] -> -0.60961313 | AB184: =IFERROR(VLOOKUP(Superstone_data[[#This Row],[Order ID]], Returns!A:B, 2, FALSE), "No") -> No | AC184: =VLOOKUP(Superstone_data[[#This Row],[Region]], Users!A:B, 2, FALSE) -> William
A185: 23481 | B185: Medium | C185: 0.08 | D185: 7.77 | E185: 9.23 | F185: 339 | G185: Bobby Clements | H185: Regular Air | I185: Corporate | J185: Office Supplies | K185: Appliances | L185: Small Box | M185: Hoover Commercial Soft Guard Upright Vacuum And Disposable Filtration Bags | N185: 0.58 | O185: United States | P185: East | Q185: Ohio | R185: Columbus | S185: 43229 | T185: 42080 | U185: 42081 | V185: -83.65 | W185: 5 | X185: 40.3 | Y185: 90583 | Z185: =TEXT(Superstone_data[[#This Row],[Order Date]],"mmm") -> Mar | AA185: =Superstone_data[[#This Row],[Profit]]/Superstone_data[[#This Row],[Sales]] -> -2.0756824 | AB185: =IFERROR(VLOOKUP(Superstone_data[[#This Row],[Order ID]], Returns!A:B, 2, FALSE), "No") -> No | AC185: =VLOOKUP(Superstone_data[[#This Row],[Region]], Users!A:B, 2, FALSE) -> Erin
A186: 23482 | B186: Medium | C186: 0.07 | D186: 7.59 | E186: 4 | F186: 339 | G186: Bobby Clements | H186: Regular Air | I186: Corporate | J186: Furniture | K186: Office Furnishings | L186: Wrap Bag | M186: Master Giant Foot® Doorstop, Safety Yellow | N186: 0.42 | O186: United States | P186: East | Q186: Ohio | R186: Columbus | S186: 43229 | T186: 42080 | U186: 42082 | V186: 24.39 | W186: 15 | X186: 111.88 | Y186: 90583 | Z186: =TEXT(Superstone_data[[#This Row],[Order Date]],"mmm") -> Mar | AA186: =Superstone_data[[#This Row],[Profit]]/Superstone_data[[#This Row],[Sales]] -> 0.21800143 | AB186: =IFERROR(VLOOKUP(Superstone_data[[#This Row],[Order ID]], Returns!A:B, 2, FALSE), "No") -> No | AC186: =VLOOKUP(Superstone_data[[#This Row],[Region]], Users!A:B, 2, FALSE) -> Erin
A187: 480 | B187: Critical | C187: 0.01 | D187: 3.26 | E187: 1.86 | F187: 342 | G187: Jacqueline Noble | H187: Regular Air | I187: Corporate | J187: Office Supplies | K187: Pens & Art Supplies | L187: Wrap Bag | M187: Avery Hi-Liter GlideStik Fluorescent Highlighter, Yellow Ink | N187: 0.41 | O187: United States | P187: South | Q187: Florida | R187: Miami | S187: 33181 | T187: 42128 | U187: 42130 | V187: -4.6683 | W187: 20 | X187: 73.97 | Y187: 3332 | Z187: =TEXT(Superstone_data[[#This Row],[Order Date]],"mmm") -> May | AA187: =Superstone_data[[#This Row],[Profit]]/Superstone_data[[#This Row],[Sales]] -> -0.063110721 | AB187: =IFERROR(VLOOKUP(Superstone_data[[#This Row],[Order ID]], Returns!A:B, 2, FALSE), "No") -> No | AC187: =VLOOKUP(Superstone_data[[#This Row],[Region]], Users!A:B, 2, FALSE) -> Sam
A188: 22784 | B188: Critical | C188: 0.03 | D188: 15.23 | E188: 27.75 | F188: 343 | G188: Lynn Epstein | H188: Delivery Truck | I188: Corporate | J188: Furniture | K188: Tables | L188: Jumbo Box | M188: Anderson Hickey Conga Table Tops & Accessories | N188: 0.76 | O188: United States | P188: East | Q188: Maine | R188: Bangor | S188: 4401 | T188: 42035 | U188: 42036 | V188: 11.65095 | W188: 7 | X188: 111.86 | Y188: 88151 | Z188: =TEXT(Superstone_data[[#This Row],[Order Date]],"mmm") -> Jan | AA188: =Superstone_data[[#This Row],[Profit]]/Superstone_data[[#This Row],[Sales]] -> 0.10415653 | AB188: =IFERROR(VLOOKUP(Superstone_data[[#This Row],[Order ID]], Returns!A:B, 2, FALSE), "No") -> No | AC188: =VLOOKUP(Superstone_data[[#This Row],[Region]], Users!A:B, 2, FALSE) -> Erin
A189: 18480 | B189: Critical | C189: 0.01 | D189: 3.26 | E189: 1.86 | F189: 344 | G189: Rosemary English | H189: Regular Air | I189: Corporate | J189: Office Supplies | K189: Pens & Art Supplies | L189: Wrap Bag | M189: Avery Hi-Liter GlideStik Fluorescent Highlighter, Yellow Ink | N189: 0.41 | O189: United States | P189: East | Q189: Maine | R189: Portland | S189: 4101 | T189: 42128 | U189: 42130 | V189: 0.702 | W189: 5 | X189: 18.49 | Y189: 88152 | Z189: =TEXT(Superstone_data[[#This Row],[Order Date]],"mmm") -> May | AA189: =Superstone_data[[#This Row],[Profit]]/Superstone_data[[#This Row],[Sales]] -> 0.037966468 | AB189: =IFERROR(VLOOKUP(Superstone_data[[#This Row],[Order ID]], Returns!A:B, 2, FALSE), "No") -> No | AC189: =VLOOKUP(Superstone_data[[#This Row],[Region]], Users!A:B, 2, FALSE) -> Erin
A190: 2408 | B190: Critical | C190: 0 | D190: 8.34 | E190: 2.64 | F190: 349 | G190: Kim Weiss | H190: Express Air | I190: Home Office | J190: Office Supplies | K190: Scissors, Rulers and Trimmers | L190: Small Pack | M190: Acme® Elite Stainless Steel Scissors | N190: 0.59 | O190: United States | P190: South | Q190: Florida | R190: Miami | S190: 33132 | T190: 42164 | U190: 42166 | V190: 5.8625 | W190: 23 | X190: 212.89 | Y190: 17446 | Z190: =TEXT(Superstone_data[[#This Row],[Order Date]],"mmm") -> Jun | AA190: =Superstone_data[[#This Row],[Profit]]/Superstone_data[[#This Row],[Sales]] -> 0.027537696 | AB190: =IFERROR(VLOOKUP(Superstone_data[[#This Row],[Order ID]], Returns!A:B, 2, FALSE), "No") -> No | AC190: =VLOOKUP(Superstone_data[[#This Row],[Region]], Users!A:B, 2, FALSE) -> Sam
A191: 1595 | B191: Medium | C191: 0.04 | D191: 99.23 | E191: 8.99 | F191: 349 | G191: Kim Weiss | H191: Regular Air | I191: Home Office | J191: Furniture | K191: Office Furnishings | L191: Small Pack | M191: GE 48" Fluorescent Tube, Cool White Energy Saver, 34 Watts, 30/Box | N191: 0.35 | O191: United States | P191: South | Q191: Florida | R191: Miami | S191: 33132 | T191: 42006 | U191: 42008 | V191: 1916.6757 | W191: 54 | X191: 5555.6 | Y191: 11527 | Z191: =TEXT(Superstone_data[[#This Row],[Order Date]],"mmm") -> Jan | AA191: =Superstone_data[[#This Row],[Profit]]/Superstone_data[[#This Row],[Sales]] -> 0.34499887 | AB191: =IFERROR(VLOOKUP(Superstone_data[[#This Row],[Order ID]], Returns!A:B, 2, FALSE), "No") -> No | AC191: =VLOOKUP(Superstone_data[[#This Row],[Region]], Users!A:B, 2, FALSE) -> Sam
A192: 20408 | B192: Critical | C192: 0 | D192: 8.34 | E192: 2.64 | F192: 351 | G192: Juanita Coley Knox | H192: Express Air | I192: Home Office | J192: Office Supplies | K192: Scissors, Rulers and Trimmers | L192: Small Pack | M192: Acme® Elite Stainless Steel Scissors | N192: 0.59 | O192: United States | P192: East | Q192: New York | R192: Watertown | S192: 13601 | T192: 42164 | U192: 42166 | V192: 10.5 | W192: 6 | X192: 55.54 | Y192: 88685 | Z192: =TEXT(Superstone_data[[#This Row],[Order Date]],"mmm") -> Jun | AA192: =Superstone_data[[#This Row],[Profit]]/Superstone_data[[#This Row],[Sales]] -> 0.18905293 | AB192: =IFERROR(VLOOKUP(Superstone_data[[#This Row],[Order ID]], Returns!A:B, 2, FALSE), "No") -> No | AC192: =VLOOKUP(Superstone_data[[#This Row],[Region]], Users!A:B, 2, FALSE) -> Erin
A193: 19595 | B193: Medium | C193: 0.04 | D193: 99.23 | E193: 8.99 | F193: 351 | G193: Juanita Coley Knox | H193: Regular Air | I193: Home Office | J193: Furniture | K193: Office Furnishings | L193: Small Pack | M193: GE 48" Fluorescent Tube, Cool White Energy Saver, 34 Watts, 30/Box | N193: 0.35 | O193: United States | P193: East | Q193: New York | R193: Watertown | S193: 13601 | T193: 42006 | U193: 42008 | V193: 993.8346 | W193: 14 | X193: 1440.34 | Y193: 88686 | Z193: =TEXT(Superstone_data[[#This Row],[Order Date]],"mmm") -> Jan | AA193: =Superstone_data[[#This Row],[Profit]]/Superstone_data[[#This Row],[Sales]] -> 0.69 | AB193: =IFERROR(VLOOKUP(Superstone_data[[#This Row],[Order ID]], Returns!A:B, 2, FALSE), "No") -> No | AC193: =VLOOKUP(Superstone_data[[#This Row],[Region]], Users!A:B, 2, FALSE) -> Erin
A194: 19107 | B194: Low | C194: 0.08 | D194: 4.89 | E194: 4.93 | F194: 353 | G194: Bonnie Chambers | H194: Express Air | I194: Home Office | J194: Technology | K194: Computer Peripherals | L194: Small Pack | M194: Maxell 3.5" DS/HD IBM-Formatted Diskettes, 10/Pack | N194: 0.66 | O194: United States | P194: West | Q194: Arizona | R194: Glendale | S194: 85301 | T194: 42138 | U194: 42138 | V194: -165.45 | W194: 17 | X194: 84.76 | Y194: 89647 | Z194: =TEXT(Superstone_data[[#This Row],[Order Date]],"mmm") -> May | AA194: =Superstone_data[[#This Row],[Profit]]/Superstone_data[[#This Row],[Sales]] -> -1.9519821 | AB194: =IFERROR(VLOOKUP(Superstone_data[[#This Row],[Order ID]], Returns!A:B, 2, FALSE), "No") -> No | AC194: =VLOOKUP(Superstone_data[[#This Row],[Region]], Users!A:B, 2, FALSE) -> William
A195: 19108 | B195: Low | C195: 0.07 | D195: 6.68 | E195: 6.92 | F195: 353 | G195: Bonnie Chambers | H195: Regular Air | I195: Home Office | J195: Office Supplies | K195: Paper | L195: Small Box | M195: Xerox 1898 | N195: 0.37 | O195: United States | P195: West | Q195: Arizona | R195: Glendale | S195: 85301 | T195: 42138 | U195: 42145 | V195: -141.12 | W195: 16 | X195: 104.84 | Y195: 89647 | Z195: =TEXT(Superstone_data[[#This Row],[Order Date]],"mmm") -> May | AA195: =Superstone_data[[#This Row],[Profit]]/Superstone_data[[#This Row],[Sales]] -> -1.3460511 | AB195: =IFERROR(VLOOKUP(Superstone_data[[#This Row],[Order ID]], Returns!A:B, 2, FALSE), "No") -> No | AC195: =VLOOKUP(Superstone_data[[#This Row],[Region]], Users!A:B, 2, FALSE) -> William
... A272: 21958 | B272: High | C272: 0.01 | D272: 20.98 | E272: 53.03 | F272: 508 | G272: Cameron Owens | H272: Delivery Truck | I272: Corporate | J272: Office Supplies | K272: Storage & Organization | L272: Jumbo Drum | M272: Tennsco Lockers, Gray | N272: 0.78 | O272: United States | P272: South | Q272: Kentucky | R272: Covington | S272: 41011 | T272: 42058 | U272: 42058 | V272: -282.0818 | W272: 5 | X272: 123 | Y272: 87356 | Z272: =TEXT(Superstone_data[[#This Row],[Order Date]],"mmm") -> Feb | AA272: =Superstone_data[[#This Row],[Profit]]/Superstone_data[[#This Row],[Sales]] -> -2.293348 | AB272: =IFERROR(VLOOKUP(Superstone_data[[#This Row],[Order ID]], Returns!A:B, 2, FALSE), "No") -> No | AC272: =VLOOKUP(Superstone_data[[#This Row],[Region]], Users!A:B, 2, FALSE) -> Sam
A273: 18305 | B273: Critical | C273: 0.01 | D273: 128.24 | E273: 12.65 | F273: 508 | G273: Cameron Owens | H273: Regular Air | I273: Corporate | J273: Furniture | K273: Chairs & Chairmats | L273: Medium Box | M273: SAFCO Folding Chair Trolley | O273: United States | P273: South | Q273: Kentucky | R273: Covington | S273: 41011 | T273: 42112 | U273: 42115 | V273: 140.1354 | W273: 4 | X273: 554.08 | Y273: 87357 | Z273: =TEXT(Superstone_data[[#This Row],[Order Date]],"mmm") -> Apr | AA273: =Superstone_data[[#This Row],[Profit]]/Superstone_data[[#This Row],[Sales]] -> 0.25291546 | AB273: =IFERROR(VLOOKUP(Superstone_data[[#This Row],[Order ID]], Returns!A:B, 2, FALSE), "No") -> No | AC273: =VLOOKUP(Superstone_data[[#This Row],[Region]], Users!A:B, 2, FALSE) -> Sam
A274: 19895 | B274: Low | C274: 0.02 | D274: 48.04 | E274: 5.09 | F274: 510 | G274: Gregory Rao | H274: Regular Air | I274: Corporate | J274: Office Supplies | K274: Paper | L274: Small Box | M274: Xerox 1910 | N274: 0.37 | O274: United States | P274: West | Q274: California | R274: Manteca | S274: 95336 | T274: 42017 | U274: 42017 | V274: 105.2526 | W274: 3 | X274: 152.54 | Y274: 90058 | Z274: =TEXT(Superstone_data[[#This Row],[Order Date]],"mmm") -> Jan | AA274: =Superstone_data[[#This Row],[Profit]]/Superstone_data[[#This Row],[Sales]] -> 0.69 | AB274: =IFERROR(VLOOKUP(Superstone_data[[#This Row],[Order ID]], Returns!A:B, 2, FALSE), "No") -> No | AC274: =VLOOKUP(Superstone_data[[#This Row],[Region]], Users!A:B, 2, FALSE) -> William
A275: 20007 | B275: Critical | C275: 0.03 | D275: 6.37 | E275: 5.19 | F275: 510 | G275: Gregory Rao | H275: Regular Air | I275: Corporate | J275: Office Supplies | K275: Binders and Binder Accessories | L275: Small Box | M275: C-Line Peel & Stick Add-On Filing Pockets, 8-3/4 x 5-1/8, 10/Pack | N275: 0.38 | O275: United States | P275: West | Q275: California | R275: Manteca | S275: 95336 | T275: 42036 | U275: 42037 | V275: -29.0927 | W275: 14 | X275: 89.79 | Y275: 90059 | Z275: =TEXT(Superstone_data[[#This Row],[Order Date]],"mmm") -> Feb | AA275: =Superstone_data[[#This Row],[Profit]]/Superstone_data[[#This Row],[Sales]] -> -0.32400824 | AB275: =IFERROR(VLOOKUP(Superstone_data[[#This Row],[Order ID]], Returns!A:B, 2, FALSE), "No") -> No | AC275: =VLOOKUP(Superstone_data[[#This Row],[Region]], Users!A:B, 2, FALSE) -> William
A276: 20216 | B276: Low | C276: 0.07 | D276: 12.64 | E276: 4.98 | F276: 518 | G276: Mark Ritchie | H276: Regular Air | I276: Home Office | J276: Furniture | K276: Office Furnishings | L276: Small Pack | M276: Nu-Dell Executive Frame | N276: 0.48 | O276: United States | P276: Central | Q276: Missouri | R276: Clayton | S276: 63105 | T276: 42160 | U276: 42167 | V276: 113.415 | W276: 16 | X276: 199.76 | Y276: 90867 | Z276: =TEXT(Superstone_data[[#This Row],[Order Date]],"mmm") -> Jun | AA276: =Superstone_data[[#This Row],[Profit]]/Superstone_data[[#This Row],[Sales]] -> 0.56775631 | AB276: =IFERROR(VLOOKUP(Superstone_data[[#This Row],[Order ID]], Returns!A:B, 2, FALSE), "No") -> No | AC276: =VLOOKUP(Superstone_data[[#This Row],[Region]], Users!A:B, 2, FALSE) -> Chris
A277: 23200 | B277: Medium | C277: 0.02 | D277: 150.98 | E277: 13.99 | F277: 522 | G277: Aaron Riggs | H277: Express Air | I277: Small Business | J277: Technology | K277: Office Machines | L277: Medium Box | M277: Canon MP41DH Printing Calculator | N277: 0.38 | O277: United States | P277: West | Q277: Oregon | R277: Redmond | S277: 97756 | T277: 42177 | U277: 42179 | V277: 26.1 | W277: 3 | X277: 480.37 | Y277: 89327 | Z277: =TEXT(Superstone_data[[#This Row],[Order Date]],"mmm") -> Jun | AA277: =Superstone_data[[#This Row],[Profit]]/Superstone_data[[#This Row],[Sales]] -> 0.054333118 | AB277: =IFERROR(VLOOKUP(Superstone_data[[#This Row],[Order ID]], Returns!A:B, 2, FALSE), "No") -> No | AC277: =VLOOKUP(Superstone_data[[#This Row],[Region]], Users!A:B, 2, FALSE) -> William
A278: 23201 | B278: Medium | C278: 0.1 | D278: 5.43 | E278: 0.95 | F278: 522 | G278: Aaron Riggs | H278: Regular Air | I278: Small Business | J278: Office Supplies | K278: Paper | L278: Wrap Bag | M278: Wirebound Message Book, 4 per Page | N278: 0.36 | O278: United States | P278: West | Q278: Oregon | R278: Redmond | S278: 97756 | T278: 42177 | U278: 42179 | V278: -2.58 | W278: 1 | X278: 5.76 | Y278: 89327 | Z278: =TEXT(Superstone_data[[#This Row],[Order Date]],"mmm") -> Jun | AA278: =Superstone_data[[#This Row],[Profit]]/Superstone_data[[#This Row],[Sales]] -> -0.44791667 | AB278: =IFERROR(VLOOKUP(Superstone_data[[#This Row],[Order ID]], Returns!A:B, 2, FALSE), "No") -> No | AC278: =VLOOKUP(Superstone_data[[#This Row],[Region]], Users!A:B, 2, FALSE) -> William
A279: 23202 | B279: Medium | C279: 0.01 | D279: 179.29 | E279: 29.21 | F279: 522 | G279: Aaron Riggs | H279: Delivery Truck | I279: Small Business | J279: Furniture | K279: Tables | L279: Jumbo Box | M279: Bevis Round Conference Table Top, X-Base | N279: 0.74 | O279: United States | P279: West | Q279: Oregon | R279: Redmond | S279: 97756 | T279: 42177 | U279: 42178 | V279: 2800.12 | W279: 21 | X279: 3112.13 | Y279: 89327 | Z279: =TEXT(Superstone_data[[#This Row],[Order Date]],"mmm") -> Jun | AA279: =Superstone_data[[#This Row],[Profit]]/Superstone_data[[#This Row],[Sales]] -> 0.89974391 | AB279: =IFERROR(VLOOKUP(Superstone_data[[#This Row],[Order ID]], Returns!A:B, 2, FALSE), "No") -> No | AC279: =VLOOKUP(Superstone_data[[#This Row],[Region]], Users!A:B, 2, FALSE) -> William
A280: 21517 | B280: Not Specified | C280: 0.03 | D280: 1270.99 | E280: 19.99 | F280: 524 | G280: Gina McKnight | H280: Regular Air | I280: Consumer | J280: Office Supplies | K280: Binders and Binder Accessories | L280: Small Box | M280: Fellowes PB500 Electric Punch Plastic Comb Binding Machine with Manual Bind | N280: 0.35 | O280: United States | P280: South | Q280: Tennessee | R280: Farragut | S280: 37922 | T280: 42024 | U280: 42026 | V280: 363.552 | W280: 2 | X280: 2589.01 | Y280: 91127 | Z280: =TEXT(Superstone_data[[#This Row],[Order Date]],"mmm") -> Jan | AA280: =Superstone_data[[#This Row],[Profit]]/Superstone_data[[#This Row],[Sales]] -> 0.14042124 | AB280: =IFERROR(VLOOKUP(Superstone_data[[#This Row],[Order ID]], Returns!A:B, 2, FALSE), "No") -> No | AC280: =VLOOKUP(Superstone_data[[#This Row],[Region]], Users!A:B, 2, FALSE) -> Sam
A281: 21518 | B281: Not Specified | C281: 0.07 | D281: 2036.48 | E281: 14.7 | F281: 524 | G281: Gina McKnight | H281: Delivery Truck | I281: Consumer | J281: Technology | K281: Office Machines | L281: Jumbo Drum | M281: Lexmark 4227 Plus Dot Matrix Printer | N281: 0.55 | O281: United States | P281: South | Q281: Tennessee | R281: Farragut | S281: 37922 | T281: 42024 | U281: 42026 | V281: -11.536 | W281: 1 | X281: 1893.93 | Y281: 91127 | Z281: =TEXT(Superstone_data[[#This Row],[Order Date]],"mmm") -> Jan | AA281: =Superstone_data[[#This Row],[Profit]]/Superstone_data[[#This Row],[Sales]] -> -0.0060910382 | AB281: =IFERROR(VLOOKUP(Superstone_data[[#This Row],[Order ID]], Returns!A:B, 2, FALSE), "No") -> No | AC281: =VLOOKUP(Superstone_data[[#This Row],[Region]], Users!A:B, 2, FALSE) -> Sam
A282: 22176 | B282: High | C282: 0.09 | D282: 17.98 | E282: 8.51 | F282: 526 | G282: April Hu | H282: Regular Air | I282: Home Office | J282: Technology | K282: Office Machines | L282: Medium Box | M282: Canon P1-DHIII Palm Printing Calculator | N282: 0.4 | O282: United States | P282: West | Q282: Arizona | R282: Mesa | S282: 85204 | T282: 42149 | U282: 42151 | V282: -6.612 | W282: 12 | X282: 211.13 | Y282: 90026 | Z282: =TEXT(Superstone_data[[#This Row],[Order Date]],"mmm") -> May | AA282: =Superstone_data[[#This Row],[Profit]]/Superstone_data[[#This Row],[Sales]] -> -0.031317198 | AB282: =IFERROR(VLOOKUP(Superstone_data[[#This Row],[Order ID]], Returns!A:B, 2, FALSE), "No") -> No | AC282: =VLOOKUP(Superstone_data[[#This Row],[Region]], Users!A:B, 2, FALSE) -> William
A283: 20494 | B283: Not Specified | C283: 0 | D283: 1.88 | E283: 1.49 | F283: 526 | G283: April Hu | H283: Regular Air | I283: Home Office | J283: Office Supplies | K283: Binders and Binder Accessories | L283: Small Box | M283: Staples® General Use 3-Ring Binders | N283: 0.37 | O283: United States | P283: West | Q283: Arizona | R283: Mesa | S283: 85204 | T283: 42021 | U283: 42022 | V283: -15.5595 | W283: 13 | X283: 25.39 | Y283: 90027 | Z283: =TEXT(Superstone_data[[#This Row],[Order Date]],"mmm") -> Jan | AA283: =Superstone_data[[#This Row],[Profit]]/Superstone_data[[#This Row],[Sales]] -> -0.61282001 | AB283: =IFERROR(VLOOKUP(Superstone_data[[#This Row],[Order ID]], Returns!A:B, 2, FALSE), "No") -> No | AC283: =VLOOKUP(Superstone_data[[#This Row],[Region]], Users!A:B, 2, FALSE) -> William
A284: 20495 | B284: Not Specified | C284: 0.06 | D284: 5.78 | E284: 5.67 | F284: 526 | G284: April Hu | H284: Regular Air | I284: Home Office | J284: Office Supplies | K284: Paper | L284: Small Box | M284: Xerox 1978 | N284: 0.36 | O284: United States | P284: West | Q284: Arizona | R284: Mesa | S284: 85204 | T284: 42021 | U284: 42022 | V284: -108.19 | W284: 15 | X284: 87.27 | Y284: 90027 | Z284: =TEXT(Superstone_data[[#This Row],[Order Date]],"mmm") -> Jan | AA284: =Superstone_data[[#This Row],[Profit]]/Superstone_data[[#This Row],[Sales]] -> -1.2397158 | AB284: =IFERROR(VLOOKUP(Superstone_data[[#This Row],[Order ID]], Returns!A:B, 2, FALSE), "No") -> No | AC284: =VLOOKUP(Superstone_data[[#This Row],[Region]], Users!A:B, 2, FALSE) -> William
A285: 26210 | B285: Low | C285: 0 | D285: 15.99 | E285: 13.18 | F285: 535 | G285: Jill Clements | H285: Regular Air | I285: Corporate | J285: Office Supplies | K285: Binders and Binder Accessories | L285: Small Box | M285: GBC Pre-Punched Binding Paper, Plastic, White, 8-1/2" x 11" | N285: 0.37 | O285: United States | P285: South | Q285: Virginia | R285: Montclair | S285: 22025 | T285: 42115 | U285: 42119 | V285: 46.488 | W285: 23 | X285: 403.25 | Y285: 88511 | Z285: =TEXT(Superstone_data[[#This Row],[Order Date]],"mmm") -> Apr | AA285: =Superstone_data[[#This Row],[Profit]]/Superstone_data[[#This Row],[Sales]] -> 0.11528332 | AB285: =IFERROR(VLOOKUP(Superstone_data[[#This Row],[Order ID]], Returns!A:B, 2, FALSE), "No") -> No | AC285: =VLOOKUP(Superstone_data[[#This Row],[Region]], Users!A:B, 2, FALSE) -> Sam
... A484: 24763 | B484: Critical | C484: 0.06 | D484: 6.48 | E484: 8.88 | F484: 868 | G484: Sharon Ellis | H484: Regular Air | I484: Corporate | J484: Office Supplies | K484: Paper | L484: Small Box | M484: Xerox 224 | N484: 0.37 | O484: United States | P484: Central | Q484: Minnesota | R484: Shoreview | S484: 55126 | T484: 42069 | U484: 42070 | V484: -237.47 | W484: 20 | X484: 125.77 | Y484: 91195 | Z484: =TEXT(Superstone_data[[#This Row],[Order Date]],"mmm") -> Mar | AA484: =Superstone_data[[#This Row],[Profit]]/Superstone_data[[#This Row],[Sales]] -> -1.8881291 | AB484: =IFERROR(VLOOKUP(Superstone_data[[#This Row],[Order ID]], Returns!A:B, 2, FALSE), "No") -> No | AC484: =VLOOKUP(Superstone_data[[#This Row],[Region]], Users!A:B, 2, FALSE) -> Chris
A485: 24764 | B485: Critical | C485: 0.09 | D485: 349.45 | E485: 60 | F485: 868 | G485: Sharon Ellis | H485: Delivery Truck | I485: Corporate | J485: Furniture | K485: Tables | L485: Jumbo Drum | M485: SAFCO PlanMaster Heigh-Adjustable Drafting Table Base, 43w x 30d x 30-37h, Black | O485: United States | P485: Central | Q485: Minnesota | R485: Shoreview | S485: 55126 | T485: 42069 | U485: 42070 | V485: -2946.051 | W485: 12 | X485: 3918.98 | Y485: 91195 | Z485: =TEXT(Superstone_data[[#This Row],[Order Date]],"mmm") -> Mar | AA485: =Superstone_data[[#This Row],[Profit]]/Superstone_data[[#This Row],[Sales]] -> -0.75173923 | AB485: =IFERROR(VLOOKUP(Superstone_data[[#This Row],[Order ID]], Returns!A:B, 2, FALSE), "No") -> No | AC485: =VLOOKUP(Superstone_data[[#This Row],[Region]], Users!A:B, 2, FALSE) -> Chris
A486: 25507 | B486: Not Specified | C486: 0.03 | D486: 14.2 | E486: 5.3 | F486: 871 | G486: Sandy Ellington | H486: Regular Air | I486: Home Office | J486: Furniture | K486: Office Furnishings | L486: Wrap Bag | M486: Coloredge Poster Frame | N486: 0.46 | O486: United States | P486: West | Q486: Nevada | R486: Reno | S486: 89502 | T486: 42078 | U486: 42080 | V486: 21.5556 | W486: 2 | X486: 31.24 | Y486: 90577 | Z486: =TEXT(Superstone_data[[#This Row],[Order Date]],"mmm") -> Mar | AA486: =Superstone_data[[#This Row],[Profit]]/Superstone_data[[#This Row],[Sales]] -> 0.69 | AB486: =IFERROR(VLOOKUP(Superstone_data[[#This Row],[Order ID]], Returns!A:B, 2, FALSE), "No") -> No | AC486: =VLOOKUP(Superstone_data[[#This Row],[Region]], Users!A:B, 2, FALSE) -> William
A487: 22547 | B487: Not Specified | C487: 0.01 | D487: 5.94 | E487: 9.92 | F487: 871 | G487: Sandy Ellington | H487: Regular Air | I487: Home Office | J487: Office Supplies | K487: Binders and Binder Accessories | L487: Small Box | M487: Storex Dura Pro™ Binders | N487: 0.38 | O487: United States | P487: West | Q487: Nevada | R487: Reno | S487: 89502 | T487: 42144 | U487: 42147 | V487: -239.315 | W487: 12 | X487: 74.77 | Y487: 90578 | Z487: =TEXT(Superstone_data[[#This Row],[Order Date]],"mmm") -> May | AA487: =Superstone_data[[#This Row],[Profit]]/Superstone_data[[#This Row],[Sales]] -> -3.2006821 | AB487: =IFERROR(VLOOKUP(Superstone_data[[#This Row],[Order ID]], Returns!A:B, 2, FALSE), "No") -> No | AC487: =VLOOKUP(Superstone_data[[#This Row],[Region]], Users!A:B, 2, FALSE) -> William
A488: 22548 | B488: Not Specified | C488: 0 | D488: 6.48 | E488: 5.11 | F488: 871 | G488: Sandy Ellington | H488: Regular Air | I488: Home Office | J488: Office Supplies | K488: Paper | L488: Small Box | M488: Xerox 231 | N488: 0.37 | O488: United States | P488: West | Q488: Nevada | R488: Reno | S488: 89502 | T488: 42144 | U488: 42146 | V488: -33.31 | W488: 18 | X488: 127.81 | Y488: 90578 | Z488: =TEXT(Superstone_data[[#This Row],[Order Date]],"mmm") -> May | AA488: =Superstone_data[[#This Row],[Profit]]/Superstone_data[[#This Row],[Sales]] -> -0.26062123 | AB488: =IFERROR(VLOOKUP(Superstone_data[[#This Row],[Order ID]], Returns!A:B, 2, FALSE), "No") -> No | AC488: =VLOOKUP(Superstone_data[[#This Row],[Region]], Users!A:B, 2, FALSE) -> William
A489: 19262 | B489: High | C489: 0.04 | D489: 4.37 | E489: 5.15 | F489: 875 | G489: Erika Fink | H489: Regular Air | I489: Small Business | J489: Office Supplies | K489: Appliances | L489: Small Box | M489: Eureka Sanitaire ® Multi-Pro Heavy-Duty Upright, Disposable Bags | N489: 0.59 | O489: United States | P489: West | Q489: Utah | R489: Salt Lake City | S489: 84106 | T489: 42056 | U489: 42057 | V489: -74.4796 | W489: 18 | X489: 78.59 | Y489: 89059 | Z489: =TEXT(Superstone_data[[#This Row],[Order Date]],"mmm") -> Feb | AA489: =Superstone_data[[#This Row],[Profit]]/Superstone_data[[#This Row],[Sales]] -> -0.94769818 | AB489: =IFERROR(VLOOKUP(Superstone_data[[#This Row],[Order ID]], Returns!A:B, 2, FALSE), "No") -> No | AC489: =VLOOKUP(Superstone_data[[#This Row],[Region]], Users!A:B, 2, FALSE) -> William
A490: 19263 | B490: High | C490: 0.09 | D490: 155.99 | E490: 8.99 | F490: 875 | G490: Erika Fink | H490: Regular Air | I490: Small Business | J490: Technology | K490: Telephones and Communication | L490: Small Box | M490: CF 688 | N490: 0.58 | O490: United States | P490: West | Q490: Utah | R490: Salt Lake City | S490: 84106 | T490: 42056 | U490: 42058 | V490: -232.22056 | W490: 4 | X490: 497.11 | Y490: 89059 | Z490: =TEXT(Superstone_data[[#This Row],[Order Date]],"mmm") -> Feb | AA490: =Superstone_data[[#This Row],[Profit]]/Superstone_data[[#This Row],[Sales]] -> -0.4671412 | AB490: =IFERROR(VLOOKUP(Superstone_data[[#This Row],[Order ID]], Returns!A:B, 2, FALSE), "No") -> No | AC490: =VLOOKUP(Superstone_data[[#This Row],[Region]], Users!A:B, 2, FALSE) -> William
A491: 18054 | B491: Critical | C491: 0.07 | D491: 5.68 | E491: 1.39 | F491: 880 | G491: Ellen Beck | H491: Regular Air | I491: Small Business | J491: Office Supplies | K491: Envelopes | L491: Small Box | M491: Staples Standard Envelopes | N491: 0.38 | O491: United States | P491: West | Q491: Arizona | R491: Scottsdale | S491: 85254 | T491: 42088 | U491: 42090 | V491: 18.6438 | W491: 5 | X491: 27.02 | Y491: 86153 | Z491: =TEXT(Superstone_data[[#This Row],[Order Date]],"mmm") -> Mar | AA491: =Superstone_data[[#This Row],[Profit]]/Superstone_data[[#This Row],[Sales]] -> 0.69 | AB491: =IFERROR(VLOOKUP(Superstone_data[[#This Row],[Order ID]], Returns!A:B, 2, FALSE), "No") -> No | AC491: =VLOOKUP(Superstone_data[[#This Row],[Region]], Users!A:B, 2, FALSE) -> William
A492: 18055 | B492: Critical | C492: 0.06 | D492: 22.84 | E492: 11.54 | F492: 880 | G492: Ellen Beck | H492: Regular Air | I492: Small Business | J492: Office Supplies | K492: Paper | L492: Small Box | M492: Xerox 1964 | N492: 0.39 | O492: United States | P492: West | Q492: Arizona | R492: Scottsdale | S492: 85254 | T492: 42088 | U492: 42090 | V492: -31.24 | W492: 1 | X492: 27.67 | Y492: 86153 | Z492: =TEXT(Superstone_data[[#This Row],[Order Date]],"mmm") -> Mar | AA492: =Superstone_data[[#This Row],[Profit]]/Superstone_data[[#This Row],[Sales]] -> -1.1290206 | AB492: =IFERROR(VLOOKUP(Superstone_data[[#This Row],[Order ID]], Returns!A:B, 2, FALSE), "No") -> No | AC492: =VLOOKUP(Superstone_data[[#This Row],[Region]], Users!A:B, 2, FALSE) -> William
A493: 19401 | B493: Critical | C493: 0.06 | D493: 25.98 | E493: 14.36 | F493: 885 | G493: Malcolm Robertson | H493: Delivery Truck | I493: Corporate | J493: Furniture | K493: Chairs & Chairmats | L493: Jumbo Drum | M493: Global Stack Chair without Arms, Black | N493: 0.6 | O493: United States | P493: Central | Q493: Texas | R493: Amarillo | S493: 79109 | T493: 42148 | U493: 42149 | V493: 55.888 | W493: 41 | X493: 1033.56 | Y493: 89537 | Z493: =TEXT(Superstone_data[[#This Row],[Order Date]],"mmm") -> May | AA493: =Superstone_data[[#This Row],[Profit]]/Superstone_data[[#This Row],[Sales]] -> 0.0540733 | AB493: =IFERROR(VLOOKUP(Superstone_data[[#This Row],[Order ID]], Returns!A:B, 2, FALSE), "No") -> No | AC493: =VLOOKUP(Superstone_data[[#This Row],[Region]], Users!A:B, 2, FALSE) -> Chris
A494: 26011 | B494: Critical | C494: 0.08 | D494: 1.81 | E494: 0.75 | F494: 890 | G494: Billie Fowler | H494: Regular Air | I494: Consumer | J494: Furniture | K494: Chairs & Chairmats | L494: Jumbo Drum | M494: Metal Folding Chairs, Beige, 4/Carton | N494: 0.58 | O494: United States | P494: Central | Q494: Texas | R494: Bedford | S494: 76021 | T494: 42009 | U494: 42010 | V494: 1.3224 | W494: 11 | X494: 19.97 | Y494: 89536 | Z494: =TEXT(Superstone_data[[#This Row],[Order Date]],"mmm") -> Jan | AA494: =Superstone_data[[#This Row],[Profit]]/Superstone_data[[#This Row],[Sales]] -> 0.066219329 | AB494: =IFERROR(VLOOKUP(Superstone_data[[#This Row],[Order ID]], Returns!A:B, 2, FALSE), "No") -> No | AC494: =VLOOKUP(Superstone_data[[#This Row],[Region]], Users!A:B, 2, FALSE) -> Chris
A495: 26015 | B495: Critical | C495: 0.04 | D495: 125.99 | E495: 5.26 | F495: 890 | G495: Billie Fowler | H495: Regular Air | I495: Consumer | J495: Technology | K495: Telephones and Communication | L495: Small Box | M495: 232 | N495: 0.55 | O495: United States | P495: Central | Q495: Texas | R495: Bedford | S495: 76021 | T495: 42009 | U495: 42009 | V495: 455.4207 | W495: 6 | X495: 660.03 | Y495: 89536 | Z495: =TEXT(Superstone_data[[#This Row],[Order Date]],"mmm") -> Jan | AA495: =Superstone_data[[#This Row],[Profit]]/Superstone_data[[#This Row],[Sales]] -> 0.69 | AB495: =IFERROR(VLOOKUP(Superstone_data[[#This Row],[Order ID]], Returns!A:B, 2, FALSE), "No") -> No | AC495: =VLOOKUP(Superstone_data[[#This Row],[Region]], Users!A:B, 2, FALSE) -> Chris
A496: 2045 | B496: Critical | C496: 0.01 | D496: 8.34 | E496: 0.96 | F496: 894 | G496: Gail Rankin Cole | H496: Regular Air | I496: Corporate | J496: Furniture | K496: Office Furnishings | L496: Wrap Bag | M496: Document Clip Frames | N496: 0.43 | O496: United States | P496: East | Q496: District of Columbia | R496: Washington | S496: 20024 | T496: 42014 | U496: 42016 | V496: 29.332 | W496: 24 | X496: 199.12 | Y496: 14596 | Z496: =TEXT(Superstone_data[[#This Row],[Order Date]],"mmm") -> Jan | AA496: =Superstone_data[[#This Row],[Profit]]/Superstone_data[[#This Row],[Sales]] -> 0.14730816 | AB496: =IFERROR(VLOOKUP(Superstone_data[[#This Row],[Order ID]], Returns!A:B, 2, FALSE), "No") -> No | AC496: =VLOOKUP(Superstone_data[[#This Row],[Region]], Users!A:B, 2, FALSE) -> Erin
A497: 2046 | B497: Critical | C497: 0.06 | D497: 3.28 | E497: 3.97 | F497: 894 | G497: Gail Rankin Cole | H497: Regular Air | I497: Corporate | J497: Office Supplies | K497: Pens & Art Supplies | L497: Wrap Bag | M497: Newell 337 | N497: 0.56 | O497: United States | P497: East | Q497: District of Columbia | R497: Washington | S497: 20024 | T497: 42014 | U497: 42015 | V497: -86 | W497: 19 | X497: 63.14 | Y497: 14596 | Z497: =TEXT(Superstone_data[[#This Row],[Order Date]],"mmm") -> Jan | AA497: =Superstone_data[[#This Row],[Profit]]/Superstone_data[[#This Row],[Sales]] -> -1.3620526 | AB497: =IFERROR(VLOOKUP(Superstone_data[[#This Row],[Order ID]], Returns!A:B, 2, FALSE), "No") -> No | AC497: =VLOOKUP(Superstone_data[[#This Row],[Region]], Users!A:B, 2, FALSE) -> Erin
... A661: 19184 | B661: High | C661: 0.09 | D661: 40.98 | E661: 6.5 | F661: 1178 | G661: Sandy Hunt | H661: Express Air | I661: Consumer | J661: Technology | K661: Computer Peripherals | L661: Small Box | M661: Targus USB Numeric Keypad | N661: 0.74 | O661: United States | P661: South | Q661: Florida | R661: Altamonte Springs | S661: 32701 | T661: 42103 | U661: 42105 | V661: 5.6916 | W661: 7 | X661: 267.69 | Y661: 89787 | Z661: =TEXT(Superstone_data[[#This Row],[Order Date]],"mmm") -> Apr | AA661: =Superstone_data[[#This Row],[Profit]]/Superstone_data[[#This Row],[Sales]] -> 0.021261907 | AB661: =IFERROR(VLOOKUP(Superstone_data[[#This Row],[Order ID]], Returns!A:B, 2, FALSE), "No") -> No | AC661: =VLOOKUP(Superstone_data[[#This Row],[Region]], Users!A:B, 2, FALSE) -> Sam
A662: 19185 | B662: High | C662: 0.09 | D662: 349.45 | E662: 60 | F662: 1178 | G662: Sandy Hunt | H662: Delivery Truck | I662: Consumer | J662: Furniture | K662: Tables | L662: Jumbo Drum | M662: SAFCO PlanMaster Heigh-Adjustable Drafting Table Base, 43w x 30d x 30-37h, Black | O662: United States | P662: South | Q662: Florida | R662: Altamonte Springs | S662: 32701 | T662: 42103 | U662: 42104 | V662: -369.11 | W662: 7 | X662: 2307.26 | Y662: 89787 | Z662: =TEXT(Superstone_data[[#This Row],[Order Date]],"mmm") -> Apr | AA662: =Superstone_data[[#This Row],[Profit]]/Superstone_data[[#This Row],[Sales]] -> -0.15997764 | AB662: =IFERROR(VLOOKUP(Superstone_data[[#This Row],[Order ID]], Returns!A:B, 2, FALSE), "No") -> No | AC662: =VLOOKUP(Superstone_data[[#This Row],[Region]], Users!A:B, 2, FALSE) -> Sam
A663: 19484 | B663: High | C663: 0.07 | D663: 2.61 | E663: 0.5 | F663: 1182 | G663: Jesse Williamson | H663: Regular Air | I663: Home Office | J663: Office Supplies | K663: Labels | L663: Small Box | M663: Avery 494 | N663: 0.39 | O663: United States | P663: West | Q663: Utah | R663: Spanish Fork | S663: 84660 | T663: 42147 | U663: 42147 | V663: 27.0135 | W663: 15 | X663: 39.15 | Y663: 86913 | Z663: =TEXT(Superstone_data[[#This Row],[Order Date]],"mmm") -> May | AA663: =Superstone_data[[#This Row],[Profit]]/Superstone_data[[#This Row],[Sales]] -> 0.69 | AB663: =IFERROR(VLOOKUP(Superstone_data[[#This Row],[Order ID]], Returns!A:B, 2, FALSE), "No") -> No | AC663: =VLOOKUP(Superstone_data[[#This Row],[Region]], Users!A:B, 2, FALSE) -> William
A664: 21522 | B664: Not Specified | C664: 0.04 | D664: 35.99 | E664: 3.3 | F664: 1183 | G664: Becky O'Brien | H664: Regular Air | I664: Home Office | J664: Technology | K664: Telephones and Communication | L664: Small Pack | M664: Accessory9 | N664: 0.39 | O664: United States | P664: West | Q664: Utah | R664: Springville | S664: 84663 | T664: 42184 | U664: 42184 | V664: 184.1955 | W664: 9 | X664: 266.95 | Y664: 86914 | Z664: =TEXT(Superstone_data[[#This Row],[Order Date]],"mmm") -> Jun | AA664: =Superstone_data[[#This Row],[Profit]]/Superstone_data[[#This Row],[Sales]] -> 0.69 | AB664: =IFERROR(VLOOKUP(Superstone_data[[#This Row],[Order ID]], Returns!A:B, 2, FALSE), "No") -> No | AC664: =VLOOKUP(Superstone_data[[#This Row],[Region]], Users!A:B, 2, FALSE) -> William
A665: 22190 | B665: Medium | C665: 0 | D665: 6783.02 | E665: 24.49 | F665: 1185 | G665: Lee Xu | H665: Regular Air | I665: Consumer | J665: Technology | K665: Office Machines | L665: Large Box | M665: Polycom ViewStation™ ISDN Videoconferencing Unit | N665: 0.39 | O665: United States | P665: South | Q665: Alabama | R665: Madison | S665: 35756 | T665: 42084 | U665: 42085 | V665: 4.11 | W665: 3 | X665: 20552.55 | Y665: 85938 | Z665: =TEXT(Superstone_data[[#This Row],[Order Date]],"mmm") -> Mar | AA665: =Superstone_data[[#This Row],[Profit]]/Superstone_data[[#This Row],[Sales]] -> 0.00019997519 | AB665: =IFERROR(VLOOKUP(Superstone_data[[#This Row],[Order ID]], Returns!A:B, 2, FALSE), "No") -> No | AC665: =VLOOKUP(Superstone_data[[#This Row],[Region]], Users!A:B, 2, FALSE) -> Sam
A666: 20764 | B666: Not Specified | C666: 0.08 | D666: 11.7 | E666: 6.96 | F666: 1185 | G666: Lee Xu | H666: Regular Air | I666: Consumer | J666: Office Supplies | K666: Appliances | L666: Medium Box | M666: Harmony HEPA Quiet Air Purifiers | N666: 0.5 | O666: United States | P666: South | Q666: Alabama | R666: Madison | S666: 35756 | T666: 42104 | U666: 42107 | V666: 28.566 | W666: 8 | X666: 87.8 | Y666: 85940 | Z666: =TEXT(Superstone_data[[#This Row],[Order Date]],"mmm") -> Apr | AA666: =Superstone_data[[#This Row],[Profit]]/Superstone_data[[#This Row],[Sales]] -> 0.32535308 | AB666: =IFERROR(VLOOKUP(Superstone_data[[#This Row],[Order ID]], Returns!A:B, 2, FALSE), "No") -> No | AC666: =VLOOKUP(Superstone_data[[#This Row],[Region]], Users!A:B, 2, FALSE) -> Sam
A667: 24358 | B667: Critical | C667: 0.07 | D667: 400.97 | E667: 48.26 | F667: 1186 | G667: Glenda Herbert | H667: Delivery Truck | I667: Consumer | J667: Technology | K667: Office Machines | L667: Jumbo Box | M667: Hewlett-Packard Deskjet 1220Cse Color Inkjet Printer | N667: 0.36 | O667: United States | P667: West | Q667: California | R667: Huntington Beach | S667: 92646 | T667: 42103 | U667: 42104 | V667: 2581.5591 | W667: 10 | X667: 3741.39 | Y667: 85939 | Z667: =TEXT(Superstone_data[[#This Row],[Order Date]],"mmm") -> Apr | AA667: =Superstone_data[[#This Row],[Profit]]/Superstone_data[[#This Row],[Sales]] -> 0.69 | AB667: =IFERROR(VLOOKUP(Superstone_data[[#This Row],[Order ID]], Returns!A:B, 2, FALSE), "No") -> No | AC667: =VLOOKUP(Superstone_data[[#This Row],[Region]], Users!A:B, 2, FALSE) -> William
A668: 18829 | B668: Low | C668: 0.06 | D668: 10.89 | E668: 4.5 | F668: 1189 | G668: Dwight Stephenson | H668: Regular Air | I668: Consumer | J668: Office Supplies | K668: Appliances | L668: Small Box | M668: Belkin 6 Outlet Metallic Surge Strip | N668: 0.59 | O668: United States | P668: West | Q668: California | R668: Huntington Beach | S668: 92646 | T668: 42172 | U668: 42177 | V668: -25.112 | W668: 14 | X668: 149.32 | Y668: 87584 | Z668: =TEXT(Superstone_data[[#This Row],[Order Date]],"mmm") -> Jun | AA668: =Superstone_data[[#This Row],[Profit]]/Superstone_data[[#This Row],[Sales]] -> -0.16817573 | AB668: =IFERROR(VLOOKUP(Superstone_data[[#This Row],[Order ID]], Returns!A:B, 2, FALSE), "No") -> No | AC668: =VLOOKUP(Superstone_data[[#This Row],[Region]], Users!A:B, 2, FALSE) -> William
A669: 18830 | B669: Low | C669: 0.03 | D669: 10.64 | E669: 5.16 | F669: 1189 | G669: Dwight Stephenson | H669: Regular Air | I669: Consumer | J669: Furniture | K669: Office Furnishings | L669: Small Box | M669: Eldon Expressions Punched Metal & Wood Desk Accessories, Pewter & Cherry | N669: 0.57 | O669: United States | P669: West | Q669: California | R669: Huntington Beach | S669: 92646 | T669: 42172 | U669: 42177 | V669: 17.376 | W669: 16 | X669: 177.01 | Y669: 87584 | Z669: =TEXT(Superstone_data[[#This Row],[Order Date]],"mmm") -> Jun | AA669: =Superstone_data[[#This Row],[Profit]]/Superstone_data[[#This Row],[Sales]] -> 0.098163946 | AB669: =IFERROR(VLOOKUP(Superstone_data[[#This Row],[Order ID]], Returns!A:B, 2, FALSE), "No") -> No | AC669: =VLOOKUP(Superstone_data[[#This Row],[Region]], Users!A:B, 2, FALSE) -> William
A670: 18831 | B670: Low | C670: 0.03 | D670: 7.96 | E670: 4.95 | F670: 1189 | G670: Dwight Stephenson | H670: Regular Air | I670: Consumer | J670: Furniture | K670: Office Furnishings | L670: Small Box | M670: Staples Plastic Wall Frames | N670: 0.41 | O670: United States | P670: West | Q670: California | R670: Huntington Beach | S670: 92646 | T670: 42172 | U670: 42174 | V670: 24.2604 | W670: 4 | X670: 35.16 | Y670: 87584 | Z670: =TEXT(Superstone_data[[#This Row],[Order Date]],"mmm") -> Jun | AA670: =Superstone_data[[#This Row],[Profit]]/Superstone_data[[#This Row],[Sales]] -> 0.69 | AB670: =IFERROR(VLOOKUP(Superstone_data[[#This Row],[Order ID]], Returns!A:B, 2, FALSE), "No") -> No | AC670: =VLOOKUP(Superstone_data[[#This Row],[Region]], Users!A:B, 2, FALSE) -> William
A671: 19553 | B671: Low | C671: 0.03 | D671: 28.53 | E671: 1.49 | F671: 1191 | G671: John Morse | H671: Regular Air | I671: Small Business | J671: Office Supplies | K671: Binders and Binder Accessories | L671: Small Box | M671: Lock-Up Easel 'Spel-Binder' | N671: 0.38 | O671: United States | P671: East | Q671: Connecticut | R671: New Britain | S671: 6050 | T671: 42183 | U671: 42186 | V671: 59.4405 | W671: 3 | X671: 88.84 | Y671: 87587 | Z671: =TEXT(Superstone_data[[#This Row],[Order Date]],"mmm") -> Jun | AA671: =Superstone_data[[#This Row],[Profit]]/Superstone_data[[#This Row],[Sales]] -> 0.66907362 | AB671: =IFERROR(VLOOKUP(Superstone_data[[#This Row],[Order ID]], Returns!A:B, 2, FALSE), "No") -> No | AC671: =VLOOKUP(Superstone_data[[#This Row],[Region]], Users!A:B, 2, FALSE) -> Erin
A672: 830 | B672: Low | C672: 0.03 | D672: 10.64 | E672: 5.16 | F672: 1193 | G672: Louis Parrish | H672: Regular Air | I672: Consumer | J672: Furniture | K672: Office Furnishings | L672: Small Box | M672: Eldon Expressions Punched Metal & Wood Desk Accessories, Pewter & Cherry | N672: 0.57 | O672: United States | P672: East | Q672: District of Columbia | R672: Washington | S672: 20016 | T672: 42172 | U672: 42177 | V672: 14.48 | W672: 63 | X672: 696.96 | Y672: 5984 | Z672: =TEXT(Superstone_data[[#This Row],[Order Date]],"mmm") -> Jun | AA672: =Superstone_data[[#This Row],[Profit]]/Superstone_data[[#This Row],[Sales]] -> 0.020775941 | AB672: =IFERROR(VLOOKUP(Superstone_data[[#This Row],[Order ID]], Returns!A:B, 2, FALSE), "No") -> No | AC672: =VLOOKUP(Superstone_data[[#This Row],[Region]], Users!A:B, 2, FALSE) -> Erin
A673: 831 | B673: Low | C673: 0.03 | D673: 7.96 | E673: 4.95 | F673: 1193 | G673: Louis Parrish | H673: Regular Air | I673: Consumer | J673: Furniture | K673: Office Furnishings | L673: Small Box | M673: Staples Plastic Wall Frames | N673: 0.41 | O673: United States | P673: East | Q673: District of Columbia | R673: Washington | S673: 20016 | T673: 42172 | U673: 42174 | V673: 22.25 | W673: 17 | X673: 149.41 | Y673: 5984 | Z673: =TEXT(Superstone_data[[#This Row],[Order Date]],"mmm") -> Jun | AA673: =Superstone_data[[#This Row],[Profit]]/Superstone_data[[#This Row],[Sales]] -> 0.14891908 | AB673: =IFERROR(VLOOKUP(Superstone_data[[#This Row],[Order ID]], Returns!A:B, 2, FALSE), "No") -> No | AC673: =VLOOKUP(Superstone_data[[#This Row],[Region]], Users!A:B, 2, FALSE) -> Erin
A674: 4131 | B674: High | C674: 0.05 | D674: 52.4 | E674: 16.11 | F674: 1193 | G674: Louis Parrish | H674: Regular Air | I674: Consumer | J674: Office Supplies | K674: Binders and Binder Accessories | L674: Small Box | M674: Ibico Laser Imprintable Binding System Covers | N674: 0.39 | O674: United States | P674: East | Q674: District of Columbia | R674: Washington | S674: 20016 | T674: 42060 | U674: 42062 | V674: 592.5265 | W674: 85 | X674: 4556.63 | Y674: 29350 | Z674: =TEXT(Superstone_data[[#This Row],[Order Date]],"mmm") -> Feb | AA674: =Superstone_data[[#This Row],[Profit]]/Superstone_data[[#This Row],[Sales]] -> 0.13003612 | AB674: =IFERROR(VLOOKUP(Superstone_data[[#This Row],[Order ID]], Returns!A:B, 2, FALSE), "No") -> No | AC674: =VLOOKUP(Superstone_data[[#This Row],[Region]], Users!A:B, 2, FALSE) -> Erin
... A701: 19875 | B701: High | C701: 0.04 | D701: 205.99 | E701: 5.26 | F701: 1233 | G701: Gary Hester | H701: Regular Air | I701: Consumer | J701: Technology | K701: Telephones and Communication | L701: Small Box | M701: i470 | N701: 0.56 | O701: United States | P701: Central | Q701: Texas | R701: Flower Mound | S701: 75028 | T701: 42159 | U701: 42160 | V701: -0.814 | W701: 6 | X701: 1018.61 | Y701: 89376 | Z701: =TEXT(Superstone_data[[#This Row],[Order Date]],"mmm") -> Jun | AA701: =Superstone_data[[#This Row],[Profit]]/Superstone_data[[#This Row],[Sales]] -> -0.00079912822 | AB701: =IFERROR(VLOOKUP(Superstone_data[[#This Row],[Order ID]], Returns!A:B, 2, FALSE), "No") -> No | AC701: =VLOOKUP(Superstone_data[[#This Row],[Region]], Users!A:B, 2, FALSE) -> Chris
A702: 20592 | B702: Medium | C702: 0.03 | D702: 128.24 | E702: 12.65 | F702: 1237 | G702: Eva Simpson | H702: Regular Air | I702: Corporate | J702: Furniture | K702: Chairs & Chairmats | L702: Medium Box | M702: SAFCO Folding Chair Trolley | O702: United States | P702: Central | Q702: Texas | R702: Carrollton | S702: 75007 | T702: 42035 | U702: 42037 | V702: 790.464 | W702: 9 | X702: 1145.6 | Y702: 86075 | Z702: =TEXT(Superstone_data[[#This Row],[Order Date]],"mmm") -> Jan | AA702: =Superstone_data[[#This Row],[Profit]]/Superstone_data[[#This Row],[Sales]] -> 0.69 | AB702: =IFERROR(VLOOKUP(Superstone_data[[#This Row],[Order ID]], Returns!A:B, 2, FALSE), "No") -> No | AC702: =VLOOKUP(Superstone_data[[#This Row],[Region]], Users!A:B, 2, FALSE) -> Chris
A703: 18625 | B703: Not Specified | C703: 0.02 | D703: 7.38 | E703: 5.21 | F703: 1237 | G703: Eva Simpson | H703: Regular Air | I703: Corporate | J703: Furniture | K703: Office Furnishings | L703: Small Box | M703: Eldon® Expressions™ Wood Desk Accessories, Oak | N703: 0.56 | O703: United States | P703: Central | Q703: Texas | R703: Carrollton | S703: 75007 | T703: 42092 | U703: 42093 | V703: 7.74 | W703: 3 | X703: 24.52 | Y703: 86076 | Z703: =TEXT(Superstone_data[[#This Row],[Order Date]],"mmm") -> Mar | AA703: =Superstone_data[[#This Row],[Profit]]/Superstone_data[[#This Row],[Sales]] -> 0.31566069 | AB703: =IFERROR(VLOOKUP(Superstone_data[[#This Row],[Order ID]], Returns!A:B, 2, FALSE), "No") -> No | AC703: =VLOOKUP(Superstone_data[[#This Row],[Region]], Users!A:B, 2, FALSE) -> Chris
A704: 20432 | B704: Medium | C704: 0.05 | D704: 300.98 | E704: 13.99 | F704: 1237 | G704: Eva Simpson | H704: Regular Air | I704: Corporate | J704: Technology | K704: Office Machines | L704: Medium Box | M704: Polycom VoiceStation 100 | N704: 0.39 | O704: United States | P704: Central | Q704: Texas | R704: Carrollton | S704: 75007 | T704: 42149 | U704: 42150 | V704: 3985.3089 | W704: 20 | X704: 5775.81 | Y704: 86077 | Z704: =TEXT(Superstone_data[[#This Row],[Order Date]],"mmm") -> May | AA704: =Superstone_data[[#This Row],[Profit]]/Superstone_data[[#This Row],[Sales]] -> 0.69 | AB704: =IFERROR(VLOOKUP(Superstone_data[[#This Row],[Order ID]], Returns!A:B, 2, FALSE), "No") -> No | AC704: =VLOOKUP(Superstone_data[[#This Row],[Region]], Users!A:B, 2, FALSE) -> Chris
A705: 20433 | B705: Medium | C705: 0.04 | D705: 205.99 | E705: 5 | F705: 1237 | G705: Eva Simpson | H705: Express Air | I705: Corporate | J705: Technology | K705: Telephones and Communication | L705: Small Box | M705: Phone 918 | N705: 0.59 | O705: United States | P705: Central | Q705: Texas | R705: Carrollton | S705: 75007 | T705: 42149 | U705: 42150 | V705: 13.9568 | W705: 11 | X705: 1878.24 | Y705: 86077 | Z705: =TEXT(Superstone_data[[#This Row],[Order Date]],"mmm") -> May | AA705: =Superstone_data[[#This Row],[Profit]]/Superstone_data[[#This Row],[Sales]] -> 0.0074307863 | AB705: =IFERROR(VLOOKUP(Superstone_data[[#This Row],[Order ID]], Returns!A:B, 2, FALSE), "No") -> No | AC705: =VLOOKUP(Superstone_data[[#This Row],[Region]], Users!A:B, 2, FALSE) -> Chris
A706: 20593 | B706: Medium | C706: 0.01 | D706: 160.98 | E706: 30 | F706: 1238 | G706: April Bowers | H706: Delivery Truck | I706: Corporate | J706: Furniture | K706: Chairs & Chairmats | L706: Jumbo Drum | M706: Office Star - Mid Back Dual function Ergonomic High Back Chair with 2-Way Adjustable Arms | N706: 0.62 | O706: United States | P706: Central | Q706: Texas | R706: Cedar Hill | S706: 75104 | T706: 42035 | U706: 42037 | V706: 788.79 | W706: 10 | X706: 1634.67 | Y706: 86075 | Z706: =TEXT(Superstone_data[[#This Row],[Order Date]],"mmm") -> Jan | AA706: =Superstone_data[[#This Row],[Profit]]/Superstone_data[[#This Row],[Sales]] -> 0.48253776 | AB706: =IFERROR(VLOOKUP(Superstone_data[[#This Row],[Order ID]], Returns!A:B, 2, FALSE), "No") -> No | AC706: =VLOOKUP(Superstone_data[[#This Row],[Region]], Users!A:B, 2, FALSE) -> Chris
A707: 20920 | B707: Not Specified | C707: 0 | D707: 387.99 | E707: 19.99 | F707: 1241 | G707: Bradley Schroeder | H707: Regular Air | I707: Corporate | J707: Office Supplies | K707: Binders and Binder Accessories | L707: Small Box | M707: Fellowes PB300 Plastic Comb Binding Machine | N707: 0.38 | O707: United States | P707: South | Q707: Alabama | R707: Auburn | S707: 36830 | T707: 42079 | U707: 42080 | V707: -70.14 | W707: 23 | X707: 9280.72 | Y707: 90880 | Z707: =TEXT(Superstone_data[[#This Row],[Order Date]],"mmm") -> Mar | AA707: =Superstone_data[[#This Row],[Profit]]/Superstone_data[[#This Row],[Sales]] -> -0.0075576033 | AB707: =IFERROR(VLOOKUP(Superstone_data[[#This Row],[Order ID]], Returns!A:B, 2, FALSE), "No") -> No | AC707: =VLOOKUP(Superstone_data[[#This Row],[Region]], Users!A:B, 2, FALSE) -> Sam
A708: 20233 | B708: Critical | C708: 0.06 | D708: 200.97 | E708: 15.59 | F708: 1241 | G708: Bradley Schroeder | H708: Delivery Truck | I708: Small Business | J708: Technology | K708: Office Machines | L708: Jumbo Drum | M708: Hewlett-Packard Deskjet 6122 Color Inkjet Printer | N708: 0.36 | O708: United States | P708: South | Q708: Alabama | R708: Auburn | S708: 36830 | T708: 42088 | U708: 42088 | V708: 531.618 | W708: 7 | X708: 1348.83 | Y708: 90881 | Z708: =TEXT(Superstone_data[[#This Row],[Order Date]],"mmm") -> Mar | AA708: =Superstone_data[[#This Row],[Profit]]/Superstone_data[[#This Row],[Sales]] -> 0.39413269 | AB708: =IFERROR(VLOOKUP(Superstone_data[[#This Row],[Order ID]], Returns!A:B, 2, FALSE), "No") -> No | AC708: =VLOOKUP(Superstone_data[[#This Row],[Region]], Users!A:B, 2, FALSE) -> Sam
A709: 5117 | B709: High | C709: 0.1 | D709: 22.38 | E709: 15.1 | F709: 1246 | G709: Lois Hansen | H709: Regular Air | I709: Home Office | J709: Office Supplies | K709: Binders and Binder Accessories | L709: Small Box | M709: Avery Flip-Chart Easel Binder, Black | N709: 0.38 | O709: United States | P709: East | Q709: New York | R709: New York City | S709: 10009 | T709: 42099 | U709: 42100 | V709: -107.5135 | W709: 26 | X709: 564.98 | Y709: 36452 | Z709: =TEXT(Superstone_data[[#This Row],[Order Date]],"mmm") -> Apr | AA709: =Superstone_data[[#This Row],[Profit]]/Superstone_data[[#This Row],[Sales]] -> -0.19029612 | AB709: =IFERROR(VLOOKUP(Superstone_data[[#This Row],[Order ID]], Returns!A:B, 2, FALSE), "No") -> No | AC709: =VLOOKUP(Superstone_data[[#This Row],[Region]], Users!A:B, 2, FALSE) -> Erin
A710: 5118 | B710: High | C710: 0.04 | D710: 6.98 | E710: 2.83 | F710: 1246 | G710: Lois Hansen | H710: Regular Air | I710: Home Office | J710: Furniture | K710: Office Furnishings | L710: Small Pack | M710: G.E. Halogen Desk Lamp Bulbs | N710: 0.37 | O710: United States | P710: East | Q710: New York | R710: New York City | S710: 10009 | T710: 42099 | U710: 42101 | V710: 46.01 | W710: 18 | X710: 129.48 | Y710: 36452 | Z710: =TEXT(Superstone_data[[#This Row],[Order Date]],"mmm") -> Apr | AA710: =Superstone_data[[#This Row],[Profit]]/Superstone_data[[#This Row],[Sales]] -> 0.35534445 | AB710: =IFERROR(VLOOKUP(Superstone_data[[#This Row],[Order ID]], Returns!A:B, 2, FALSE), "No") -> No | AC710: =VLOOKUP(Superstone_data[[#This Row],[Region]], Users!A:B, 2, FALSE) -> Erin
A711: 6581 | B711: Low | C711: 0.03 | D711: 256.99 | E711: 11.25 | F711: 1246 | G711: Lois Hansen | H711: Regular Air | I711: Home Office | J711: Technology | K711: Computer Peripherals | L711: Small Box | M711: Hayes Optima 56K V.90 Internal Voice Modem | N711: 0.51 | O711: United States | P711: East | Q711: New York | R711: New York City | S711: 10009 | T711: 42146 | U711: 42146 | V711: 1489.8 | W711: 32 | X711: 8216.28 | Y711: 46853 | Z711: =TEXT(Superstone_data[[#This Row],[Order Date]],"mmm") -> May | AA711: =Superstone_data[[#This Row],[Profit]]/Superstone_data[[#This Row],[Sales]] -> 0.18132293 | AB711: =IFERROR(VLOOKUP(Superstone_data[[#This Row],[Order ID]], Returns!A:B, 2, FALSE), "No") -> No | AC711: =VLOOKUP(Superstone_data[[#This Row],[Region]], Users!A:B, 2, FALSE) -> Erin
A712: 23117 | B712: High | C712: 0.1 | D712: 22.38 | E712: 15.1 | F712: 1247 | G712: Henry O'Connell | H712: Regular Air | I712: Home Office | J712: Office Supplies | K712: Binders and Binder Accessories | L712: Small Box | M712: Avery Flip-Chart Easel Binder, Black | N712: 0.38 | O712: United States | P712: Central | Q712: Texas | R712: Leander | S712: 78641 | T712: 42099 | U712: 42100 | V712: -107.5135 | W712: 7 | X712: 152.11 | Y712: 91555 | Z712: =TEXT(Superstone_data[[#This Row],[Order Date]],"mmm") -> Apr | AA712: =Superstone_data[[#This Row],[Profit]]/Superstone_data[[#This Row],[Sales]] -> -0.70681415 | AB712: =IFERROR(VLOOKUP(Superstone_data[[#This Row],[Order ID]], Returns!A:B, 2, FALSE), "No") -> No | AC712: =VLOOKUP(Superstone_data[[#This Row],[Region]], Users!A:B, 2, FALSE) -> Chris
A713: 23118 | B713: High | C713: 0.04 | D713: 6.98 | E713: 2.83 | F713: 1247 | G713: Henry O'Connell | H713: Regular Air | I713: Home Office | J713: Furniture | K713: Office Furnishings | L713: Small Pack | M713: G.E. Halogen Desk Lamp Bulbs | N713: 0.37 | O713: United States | P713: Central | Q713: Texas | R713: Leander | S713: 78641 | T713: 42099 | U713: 42101 | V713: 24.8193 | W713: 5 | X713: 35.97 | Y713: 91555 | Z713: =TEXT(Superstone_data[[#This Row],[Order Date]],"mmm") -> Apr | AA713: =Superstone_data[[#This Row],[Profit]]/Superstone_data[[#This Row],[Sales]] -> 0.69 | AB713: =IFERROR(VLOOKUP(Superstone_data[[#This Row],[Order ID]], Returns!A:B, 2, FALSE), "No") -> No | AC713: =VLOOKUP(Superstone_data[[#This Row],[Region]], Users!A:B, 2, FALSE) -> Chris
A714: 18413 | B714: High | C714: 0 | D714: 3.89 | E714: 7.01 | F714: 1250 | G714: Kara Patton | H714: Regular Air | I714: Corporate | J714: Office Supplies | K714: Binders and Binder Accessories | L714: Small Box | M714: Avery Binder Labels | N714: 0.37 | O714: United States | P714: Central | Q714: Illinois | R714: Carpentersville | S714: 60110 | T714: 42103 | U714: 42103 | V714: -255.1689 | W714: 21 | X714: 85.64 | Y714: 87877 | Z714: =TEXT(Superstone_data[[#This Row],[Order Date]],"mmm") -> Apr | AA714: =Superstone_data[[#This Row],[Profit]]/Superstone_data[[#This Row],[Sales]] -> -2.9795528 | AB714: =IFERROR(VLOOKUP(Superstone_data[[#This Row],[Order ID]], Returns!A:B, 2, FALSE), "No") -> No | AC714: =VLOOKUP(Superstone_data[[#This Row],[Region]], Users!A:B, 2, FALSE) -> Chris
... A728: 22363 | B728: Critical | C728: 0.01 | D728: 13.99 | E728: 7.51 | F728: 1267 | G728: Rosemary Branch | H728: Regular Air | I728: Corporate | J728: Technology | K728: Office Machines | L728: Medium Box | M728: Sharp EL500L Fraction Calculator | N728: 0.39 | O728: United States | P728: South | Q728: Florida | R728: Boca Raton | S728: 33433 | T728: 42045 | U728: 42046 | V728: 533.742 | W728: 2 | X728: 29.85 | Y728: 89514 | Z728: =TEXT(Superstone_data[[#This Row],[Order Date]],"mmm") -> Feb | AA728: =Superstone_data[[#This Row],[Profit]]/Superstone_data[[#This Row],[Sales]] -> 17.880804 | AB728: =IFERROR(VLOOKUP(Superstone_data[[#This Row],[Order ID]], Returns!A:B, 2, FALSE), "No") -> No | AC728: =VLOOKUP(Superstone_data[[#This Row],[Region]], Users!A:B, 2, FALSE) -> Sam
A729: 21848 | B729: Not Specified | C729: 0.08 | D729: 128.24 | E729: 12.65 | F729: 1267 | G729: Rosemary Branch | H729: Regular Air | I729: Corporate | J729: Furniture | K729: Chairs & Chairmats | L729: Medium Box | M729: SAFCO Folding Chair Trolley | O729: United States | P729: South | Q729: Florida | R729: Boca Raton | S729: 33433 | T729: 42136 | U729: 42137 | V729: -379.344 | W729: 3 | X729: 366.44 | Y729: 89515 | Z729: =TEXT(Superstone_data[[#This Row],[Order Date]],"mmm") -> May | AA729: =Superstone_data[[#This Row],[Profit]]/Superstone_data[[#This Row],[Sales]] -> -1.0352145 | AB729: =IFERROR(VLOOKUP(Superstone_data[[#This Row],[Order ID]], Returns!A:B, 2, FALSE), "No") -> No | AC729: =VLOOKUP(Superstone_data[[#This Row],[Region]], Users!A:B, 2, FALSE) -> Sam
A730: 21849 | B730: Not Specified | C730: 0.04 | D730: 5.98 | E730: 4.38 | F730: 1267 | G730: Rosemary Branch | H730: Regular Air | I730: Corporate | J730: Technology | K730: Computer Peripherals | L730: Small Pack | M730: Imation 3.5" DS/HD IBM Formatted Diskettes, 10/Pack | N730: 0.75 | O730: United States | P730: South | Q730: Florida | R730: Boca Raton | S730: 33433 | T730: 42136 | U730: 42138 | V730: -1522.304 | W730: 11 | X730: 69.75 | Y730: 89515 | Z730: =TEXT(Superstone_data[[#This Row],[Order Date]],"mmm") -> May | AA730: =Superstone_data[[#This Row],[Profit]]/Superstone_data[[#This Row],[Sales]] -> -21.825147 | AB730: =IFERROR(VLOOKUP(Superstone_data[[#This Row],[Order ID]], Returns!A:B, 2, FALSE), "No") -> No | AC730: =VLOOKUP(Superstone_data[[#This Row],[Region]], Users!A:B, 2, FALSE) -> Sam
A731: 19550 | B731: Medium | C731: 0.07 | D731: 125.99 | E731: 7.69 | F731: 1271 | G731: Joanne Church | H731: Regular Air | I731: Corporate | J731: Technology | K731: Telephones and Communication | L731: Small Box | M731: StarTAC 3000 | N731: 0.59 | O731: United States | P731: West | Q731: California | R731: La Mesa | S731: 91941 | T731: 42103 | U731: 42104 | V731: 588.2457 | W731: 8 | X731: 852.53 | Y731: 88410 | Z731: =TEXT(Superstone_data[[#This Row],[Order Date]],"mmm") -> Apr | AA731: =Superstone_data[[#This Row],[Profit]]/Superstone_data[[#This Row],[Sales]] -> 0.69 | AB731: =IFERROR(VLOOKUP(Superstone_data[[#This Row],[Order ID]], Returns!A:B, 2, FALSE), "No") -> No | AC731: =VLOOKUP(Superstone_data[[#This Row],[Region]], Users!A:B, 2, FALSE) -> William
A732: 19398 | B732: Low | C732: 0.1 | D732: 34.23 | E732: 5.02 | F732: 1271 | G732: Joanne Church | H732: Regular Air | I732: Corporate | J732: Furniture | K732: Office Furnishings | L732: Small Box | M732: Hand-Finished Solid Wood Document Frame | N732: 0.55 | O732: United States | P732: West | Q732: California | R732: La Mesa | S732: 91941 | T732: 42125 | U732: 42130 | V732: 151.5654 | W732: 7 | X732: 219.66 | Y732: 88411 | Z732: =TEXT(Superstone_data[[#This Row],[Order Date]],"mmm") -> May | AA732: =Superstone_data[[#This Row],[Profit]]/Superstone_data[[#This Row],[Sales]] -> 0.69 | AB732: =IFERROR(VLOOKUP(Superstone_data[[#This Row],[Order ID]], Returns!A:B, 2, FALSE), "No") -> No | AC732: =VLOOKUP(Superstone_data[[#This Row],[Region]], Users!A:B, 2, FALSE) -> William
A733: 20628 | B733: Critical | C733: 0.07 | D733: 40.98 | E733: 7.47 | F733: 1279 | G733: Josephine Rao | H733: Regular Air | I733: Corporate | J733: Office Supplies | K733: Binders and Binder Accessories | L733: Small Box | M733: Wilson Jones Ledger-Size, Piano-Hinge Binder, 2", Blue | N733: 0.37 | O733: United States | P733: Central | Q733: Indiana | R733: Hammond | S733: 46324 | T733: 42064 | U733: 42065 | V733: 54.9015 | W733: 2 | X733: 81.9 | Y733: 90114 | Z733: =TEXT(Superstone_data[[#This Row],[Order Date]],"mmm") -> Mar | AA733: =Superstone_data[[#This Row],[Profit]]/Superstone_data[[#This Row],[Sales]] -> 0.67034799 | AB733: =IFERROR(VLOOKUP(Superstone_data[[#This Row],[Order ID]], Returns!A:B, 2, FALSE), "No") -> No | AC733: =VLOOKUP(Superstone_data[[#This Row],[Region]], Users!A:B, 2, FALSE) -> Chris
A734: 25005 | B734: Not Specified | C734: 0 | D734: 442.14 | E734: 14.7 | F734: 1279 | G734: Josephine Rao | H734: Delivery Truck | I734: Corporate | J734: Technology | K734: Office Machines | L734: Jumbo Drum | M734: Okidata ML390 Turbo Dot Matrix Printers | N734: 0.56 | O734: United States | P734: Central | Q734: Indiana | R734: Hammond | S734: 46324 | T734: 42068 | U734: 42068 | V734: 501.51 | W734: 5 | X734: 2343.34 | Y734: 90115 | Z734: =TEXT(Superstone_data[[#This Row],[Order Date]],"mmm") -> Mar | AA734: =Superstone_data[[#This Row],[Profit]]/Superstone_data[[#This Row],[Sales]] -> 0.21401504 | AB734: =IFERROR(VLOOKUP(Superstone_data[[#This Row],[Order ID]], Returns!A:B, 2, FALSE), "No") -> No | AC734: =VLOOKUP(Superstone_data[[#This Row],[Region]], Users!A:B, 2, FALSE) -> Chris
A735: 2628 | B735: Critical | C735: 0.07 | D735: 40.98 | E735: 7.47 | F735: 1280 | G735: Harold Albright | H735: Regular Air | I735: Corporate | J735: Office Supplies | K735: Binders and Binder Accessories | L735: Small Box | M735: Wilson Jones Ledger-Size, Piano-Hinge Binder, 2", Blue | N735: 0.37 | O735: United States | P735: West | Q735: Washington | R735: Seattle | S735: 98119 | T735: 42064 | U735: 42065 | V735: 54.9015 | W735: 8 | X735: 327.61 | Y735: 19042 | Z735: =TEXT(Superstone_data[[#This Row],[Order Date]],"mmm") -> Mar | AA735: =Superstone_data[[#This Row],[Profit]]/Superstone_data[[#This Row],[Sales]] -> 0.16758188 | AB735: =IFERROR(VLOOKUP(Superstone_data[[#This Row],[Order ID]], Returns!A:B, 2, FALSE), "No") -> No | AC735: =VLOOKUP(Superstone_data[[#This Row],[Region]], Users!A:B, 2, FALSE) -> William
A736: 22125 | B736: Low | C736: 0.1 | D736: 238.4 | E736: 24.49 | F736: 1281 | G736: Pauline Denton | H736: Regular Air | I736: Small Business | J736: Furniture | K736: Chairs & Chairmats | L736: Large Box | M736: Safco Contoured Stacking Chairs | O736: United States | P736: Central | Q736: Indiana | R736: Vincennes | S736: 47591 | T736: 42028 | U736: 42030 | V736: 875.2844 | W736: 8 | X736: 1774.5 | Y736: 89112 | Z736: =TEXT(Superstone_data[[#This Row],[Order Date]],"mmm") -> Jan | AA736: =Superstone_data[[#This Row],[Profit]]/Superstone_data[[#This Row],[Sales]] -> 0.49325692 | AB736: =IFERROR(VLOOKUP(Superstone_data[[#This Row],[Order ID]], Returns!A:B, 2, FALSE), "No") -> No | AC736: =VLOOKUP(Superstone_data[[#This Row],[Region]], Users!A:B, 2, FALSE) -> Chris
A737: 22126 | B737: Low | C737: 0.03 | D737: 199.99 | E737: 24.49 | F737: 1281 | G737: Pauline Denton | H737: Express Air | I737: Small Business | J737: Technology | K737: Copiers and Fax | L737: Large Box | M737: Canon PC-428 Personal Copier | N737: 0.46 | O737: United States | P737: Central | Q737: Indiana | R737: Vincennes | S737: 47591 | T737: 42028 | U737: 42030 | V737: 727.7361 | W737: 5 | X737: 1054.69 | Y737: 89112 | Z737: =TEXT(Superstone_data[[#This Row],[Order Date]],"mmm") -> Jan | AA737: =Superstone_data[[#This Row],[Profit]]/Superstone_data[[#This Row],[Sales]] -> 0.69 | AB737: =IFERROR(VLOOKUP(Superstone_data[[#This Row],[Order ID]], Returns!A:B, 2, FALSE), "No") -> No | AC737: =VLOOKUP(Superstone_data[[#This Row],[Region]], Users!A:B, 2, FALSE) -> Chris
A738: 4125 | B738: Low | C738: 0.1 | D738: 238.4 | E738: 24.49 | F738: 1282 | G738: Dana Sharpe | H738: Regular Air | I738: Small Business | J738: Furniture | K738: Chairs & Chairmats | L738: Large Box | M738: Safco Contoured Stacking Chairs | O738: United States | P738: East | Q738: Pennsylvania | R738: Philadelphia | S738: 19134 | T738: 42028 | U738: 42030 | V738: 460.676 | W738: 30 | X738: 6654.39 | Y738: 29319 | Z738: =TEXT(Superstone_data[[#This Row],[Order Date]],"mmm") -> Jan | AA738: =Superstone_data[[#This Row],[Profit]]/Superstone_data[[#This Row],[Sales]] -> 0.069228885 | AB738: =IFERROR(VLOOKUP(Superstone_data[[#This Row],[Order ID]], Returns!A:B, 2, FALSE), "No") -> No | AC738: =VLOOKUP(Superstone_data[[#This Row],[Region]], Users!A:B, 2, FALSE) -> Erin
A739: 4126 | B739: Low | C739: 0.03 | D739: 199.99 | E739: 24.49 | F739: 1282 | G739: Dana Sharpe | H739: Express Air | I739: Small Business | J739: Technology | K739: Copiers and Fax | L739: Large Box | M739: Canon PC-428 Personal Copier | N739: 0.46 | O739: United States | P739: East | Q739: Pennsylvania | R739: Philadelphia | S739: 19134 | T739: 42028 | U739: 42030 | V739: 393.42 | W739: 21 | X739: 4429.69 | Y739: 29319 | Z739: =TEXT(Superstone_data[[#This Row],[Order Date]],"mmm") -> Jan | AA739: =Superstone_data[[#This Row],[Profit]]/Superstone_data[[#This Row],[Sales]] -> 0.088814341 | AB739: =IFERROR(VLOOKUP(Superstone_data[[#This Row],[Order ID]], Returns!A:B, 2, FALSE), "No") -> No | AC739: =VLOOKUP(Superstone_data[[#This Row],[Region]], Users!A:B, 2, FALSE) -> Erin
A740: 19990 | B740: Not Specified | C740: 0.04 | D740: 150.98 | E740: 13.99 | F740: 1298 | G740: Herbert Beard | H740: Regular Air | I740: Home Office | J740: Technology | K740: Office Machines | L740: Medium Box | M740: Canon MP41DH Printing Calculator | N740: 0.38 | O740: United States | P740: Central | Q740: Texas | R740: Sulphur Springs | S740: 75482 | T740: 42047 | U740: 42050 | V740: 606.0546 | W740: 6 | X740: 878.34 | Y740: 90662 | Z740: =TEXT(Superstone_data[[#This Row],[Order Date]],"mmm") -> Feb | AA740: =Superstone_data[[#This Row],[Profit]]/Superstone_data[[#This Row],[Sales]] -> 0.69 | AB740: =IFERROR(VLOOKUP(Superstone_data[[#This Row],[Order ID]], Returns!A:B, 2, FALSE), "No") -> No | AC740: =VLOOKUP(Superstone_data[[#This Row],[Region]], Users!A:B, 2, FALSE) -> Chris
A741: 19991 | B741: Not Specified | C741: 0.04 | D741: 176.19 | E741: 11.87 | F741: 1298 | G741: Herbert Beard | H741: Regular Air | I741: Home Office | J741: Office Supplies | K741: Storage & Organization | L741: Small Box | M741: Fellowes High-Stak® Drawer Files | N741: 0.62 | O741: United States | P741: Central | Q741: Texas | R741: Sulphur Springs | S741: 75482 | T741: 42047 | U741: 42049 | V741: 320.1 | W741: 4 | X741: 676.57 | Y741: 90662 | Z741: =TEXT(Superstone_data[[#This Row],[Order Date]],"mmm") -> Feb | AA741: =Superstone_data[[#This Row],[Profit]]/Superstone_data[[#This Row],[Sales]] -> 0.47312178 | AB741: =IFERROR(VLOOKUP(Superstone_data[[#This Row],[Order ID]], Returns!A:B, 2, FALSE), "No") -> No | AC741: =VLOOKUP(Superstone_data[[#This Row],[Region]], Users!A:B, 2, FALSE) -> Chris
A742: 23120 | B742: High | C742: 0.03 | D742: 39.48 | E742: 1.99 | F742: 1303 | G742: Cindy Harvey | H742: Regular Air | I742: Consumer | J742: Technology | K742: Computer Peripherals | L742: Small Pack | M742: 80 Minute CD-R Spindle, 100/Pack - Staples | N742: 0.54 | O742: United States | P742: West | Q742: Utah | R742: Tooele | S742: 84074 | T742: 42054 | U742: 42056 | V742: 317.0895 | W742: 12 | X742: 459.55 | Y742: 87003 | Z742: =TEXT(Superstone_data[[#This Row],[Order Date]],"mmm") -> Feb | AA742: =Superstone_data[[#This Row],[Profit]]/Superstone_data[[#This Row],[Sales]] -> 0.69 | AB742: =IFERROR(VLOOKUP(Superstone_data[[#This Row],[Order ID]], Returns!A:B, 2, FALSE), "No") -> No | AC742: =VLOOKUP(Superstone_data[[#This Row],[Region]], Users!A:B, 2, FALSE) -> William
A743: 20652 | B743: Low | C743: 0.01 | D743: 65.99 | E743: 5.31 | F743: 1303 | G743: Cindy Harvey | H743: Regular Air | I743: Consumer | J743: Technology | K743: Telephones and Communication | L743: Small Box | M743: 3390 | N743: 0.57 | O743: United States | P743: West | Q743: Utah | R743: Tooele | S743: 84074 | T743: 42054 | U743: 42061 | V743: 250.36272 | W743: 9 | X743: 536.9 | Y743: 87005 | Z743: =TEXT(Superstone_data[[#This Row],[Order Date]],"mmm") -> Feb | AA743: =Superstone_data[[#This Row],[Profit]]/Superstone_data[[#This Row],[Sales]] -> 0.46631164 | AB743: =IFERROR(VLOOKUP(Superstone_data[[#This Row],[Order ID]], Returns!A:B, 2, FALSE), "No") -> No | AC743: =VLOOKUP(Superstone_data[[#This Row],[Region]], Users!A:B, 2, FALSE) -> William
A744: 25092 | B744: Medium | C744: 0.08 | D744: 2.88 | E744: 0.5 | F744: 1304 | G744: Sherri McIntosh | H744: Regular Air | I744: Consumer | J744: Office Supplies | K744: Labels | L744: Small Box | M744: Avery 507 | N744: 0.39 | O744: United States | P744: West | Q744: Utah | R744: West Jordan | S744: 84084 | T744: 42117 | U744: 42118 | V744: 6.0306 | W744: 3 | X744: 8.74 | Y744: 87004 | Z744: =TEXT(Superstone_data[[#This Row],[Order Date]],"mmm") -> Apr | AA744: =Superstone_data[[#This Row],[Profit]]/Superstone_data[[#This Row],[Sales]] -> 0.69 | AB744: =IFERROR(VLOOKUP(Superstone_data[[#This Row],[Order ID]], Returns!A:B, 2, FALSE), "No") -> No | AC744: =VLOOKUP(Superstone_data[[#This Row],[Region]], Users!A:B, 2, FALSE) -> William
...

Sheet Returns
A1: Order ID | B1: Status
A2: 65 | B2: Returned
A3: 612 | B3: Returned
A4: 614 | B4: Returned
A5: 678 | B5: Returned
A6: 710 | B6: Returned
A7: 740 | B7: Returned
A8: 775 | B8: Returned
A9: 833 | B9: Returned
A10: 902 | B10: Returned
A11: 3300 | B11: Returned
A12: 3456 | B12: Returned
A13: 3525 | B13: Returned
... A1635: 182906 | B1635: Returned

Sheet Users
A1: Region | B1: Manager
A2: Central | B2: Chris
A3: East | B3: Erin
A4: South | B4: Sam
A5: West | B5: William

Sheet Pivots
A12: Average of Profit margin
A13: -0.33326229
A15: Total Profit | B15: Total Sales
A16: 85291.403 | B16: 592171.49 | D16: Row Labels | E16: Sum of Profit
D17: Apr | E17: 39562.479
A18: Count of Order ID | D18: Feb | E18: -3273.2288
A19: 474 | D19: Jan | E19: -7866.8671
D20: Jun | E20: 28420.945
D21: Mar | E21: 13182.673
D22: May | E22: 15265.402
A23: Row Labels | B23: Sum of Sales | D23: Grand Total | E23: 85291.403
A24: Jun | B24: 123225.09
A25: May | B25: 84858.81
A26: Apr | B26: 189208.29 | D26: Row Labels | E26: Total Profit
A27: Mar | B27: 59137.04 | D27: Furniture | E27: -462.97419
A28: Feb | B28: 69708.83 | D28: Office Supplies | E28: 51107.563
A29: Jan | B29: 66033.43 | D29: Technology | E29: 34646.815
A30: Grand Total | B30: 592171.49 | D30: Grand Total | E30: 85291.403
A36: Row Labels | B36: Count of Returned
A37: Furniture | B37: 99
A38: Office Supplies | B38: 265
A39: Technology | B39: 110
A40: Grand Total | B40: 474
A44: Row Labels | B44: Sum of Profit
A45: Rhode Island | B45: 5073.0014
A46: Massachusetts | B46: 5293.784
A47: District of Columbia | B47: 11677.363
A48: Ohio | B48: 23410.842
A49: New York | B49: 27611.943
A50: Grand Total | B50: 73066.934
A53: Row Labels | B53: Total Profit
A54: Pennsylvania | B54: -1095.5065
A55: Connecticut | B55: -529.1063
A56: Delaware | B56: 406.7418
A57: Vermont | B57: 530.14978
A58: New Jersey | B58: 770.90869
A59: Grand Total | B59: 83.187443

Sheet Dashboard
